<?xml version="1.0" encoding="UTF-8" ?><nfeProc versao="4.00" xmlns="http://www.portalfiscal.inf.br/nfe"><NFe xmlns="http://www.portalfiscal.inf.br/nfe"><infNFe Id="NFe42180860409075045253550010004211641288923571" versao="4.00"><ide><cUF>42</cUF><cNF>28892357</cNF><natOp>VDA.MERC.ADQ.REC.DE TERCEIROS</natOp><mod>55</mod><serie>1</serie><nNF>421164</nNF><dhEmi>2018-08-03T11:19:08-03:00</dhEmi><dhSaiEnt>2018-08-03T11:24:08-03:00</dhSaiEnt><tpNF>1</tpNF><idDest>1</idDest><cMunFG>4204202</cMunFG><tpImp>2</tpImp><tpEmis>1</tpEmis><cDV>1</cDV><tpAmb>1</tpAmb><finNFe>1</finNFe><indFinal>0</indFinal><indPres>9</indPres><procEmi>0</procEmi><verProc>SAP GRC NFE 4.00</verProc></ide><emit><CNPJ>60409075045253</CNPJ><xNome>Nestle Brasil Ltda</xNome><xFant>BR DC Broker ManA</xFant><enderEmit><xLgr>Av Leopoldo Sander</xLgr><nro>3514</nro><xCpl>LET E S1</xCpl><xBairro>Engenho Braun</xBairro><cMun>4204202</cMun><xMun>Chapeco</xMun><UF>SC</UF><CEP>89809300</CEP><xPais>Brasil</xPais><fone>4933307800</fone></enderEmit><IE>256899517</IE><CRT>3</CRT></emit><dest><CNPJ>79496808000161</CNPJ><xNome>Abastecedora Perizzolo Ltda</xNome><enderDest><xLgr>R Fernando Machado</xLgr><nro>1294d</nro><xBairro>Centro</xBairro><cMun>4204202</cMun><xMun>Chapeco</xMun><UF>SC</UF><CEP>89802111</CEP><cPais>1058</cPais><xPais>Brasil</xPais><fone>4933221047</fone></enderDest><indIEDest>1</indIEDest><IE>251375870</IE></dest><det nItem="1"><prod><cProd>000000000000414057</cProd><cEAN>7891000405710</cEAN><xProd>MOCA Chocolate 12(24x38g) BR</xProd><NCM>18063110</NCM><CEST>1700200</CEST><indEscala>S</indEscala><CFOP>5102</CFOP><uCom>EXB</uCom><qCom>1.0000</qCom><vUnCom>38.3700000000</vUnCom><vProd>38.37</vProd><cEANTrib>7891000405703</cEANTrib><uTrib>UNI</uTrib><qTrib>24.0000</qTrib><vUnTrib>1.5987500000</vUnTrib><indTot>1</indTot><xPed>1077651</xPed><nItemPed>000010</nItemPed><nFCI>03691D38-BD66-453D-845F-E24A2DAF1E0F</nFCI></prod><imposto><ICMS><ICMS20><orig>5</orig><CST>20</CST><modBC>3</modBC><pRedBC>29.4100</pRedBC><vBC>27.09</vBC><pICMS>17.0000</pICMS><vICMS>4.60</vICMS></ICMS20></ICMS><IPI><cEnq>999</cEnq><IPITrib><CST>99</CST><vBC>0.00</vBC><pIPI>0.0000</pIPI><vIPI>0.00</vIPI></IPITrib></IPI><PIS><PISAliq><CST>01</CST><vBC>38.37</vBC><pPIS>1.6500</pPIS><vPIS>0.63</vPIS></PISAliq></PIS><COFINS><COFINSAliq><CST>01</CST><vBC>38.37</vBC><pCOFINS>7.6000</pCOFINS><vCOFINS>2.92</vCOFINS></COFINSAliq></COFINS></imposto><infAdProd>Resolu ao do Senado Federal n  13/12,N  da FCI 03691D38-BD66-453D-845F-E24A2DAF1E0F</infAdProd></det><det nItem="2"><prod><cProd>000000000012097176</cProd><cEAN>7891000067048</cEAN><xProd>ALPINO Bebida Garrafa Plas 4(6x280ml) BR</xProd><NCM>22029900</NCM><CEST>1711500</CEST><indEscala>S</indEscala><EXTIPI>01</EXTIPI><CFOP>5102</CFOP><uCom>UNI</uCom><qCom>6.0000</qCom><vUnCom>2.8216666667</vUnCom><vProd>16.93</vProd><cEANTrib>7891000067048</cEANTrib><uTrib>UNI</uTrib><qTrib>6.0000</qTrib><vUnTrib>2.8216666667</vUnTrib><indTot>1</indTot><xPed>1077651</xPed><nItemPed>000020</nItemPed><nFCI>081FAB6A-2833-4F9A-9850-6B537E784198</nFCI></prod><imposto><ICMS><ICMS20><orig>5</orig><CST>20</CST><modBC>3</modBC><pRedBC>29.4100</pRedBC><vBC>11.95</vBC><pICMS>17.0000</pICMS><vICMS>2.03</vICMS></ICMS20></ICMS><IPI><cEnq>999</cEnq><IPINT><CST>51</CST></IPINT></IPI><PIS><PISNT><CST>06</CST></PISNT></PIS><COFINS><COFINSNT><CST>06</CST></COFINSNT></COFINS></imposto><infAdProd>Resolu ao do Senado Federal n  13/12,N  da FCI 081FAB6A-2833-4F9A-9850-6B537E784198</infAdProd></det><det nItem="3"><prod><cProd>000000000012272048</cProd><cEAN>7891000107645</cEAN><xProd>ALPINO Chocolate Leite 12(18x25g) BR</xProd><NCM>18063210</NCM><CEST>1700300</CEST><indEscala>S</indEscala><CFOP>5102</CFOP><uCom>EXB</uCom><qCom>1.0000</qCom><vUnCom>25.0400000000</vUnCom><vProd>25.04</vProd><cEANTrib>7891000107638</cEANTrib><uTrib>UNI</uTrib><qTrib>18.0000</qTrib><vUnTrib>1.3911111111</vUnTrib><indTot>1</indTot><xPed>1077651</xPed><nItemPed>000030</nItemPed><nFCI>4625CA03-2835-4B02-9FBD-497330038B70</nFCI></prod><imposto><ICMS><ICMS20><orig>5</orig><CST>20</CST><modBC>3</modBC><pRedBC>29.4100</pRedBC><vBC>17.68</vBC><pICMS>17.0000</pICMS><vICMS>3.00</vICMS></ICMS20></ICMS><IPI><cEnq>999</cEnq><IPITrib><CST>99</CST><vBC>0.00</vBC><pIPI>0.0000</pIPI><vIPI>0.00</vIPI></IPITrib></IPI><PIS><PISAliq><CST>01</CST><vBC>25.04</vBC><pPIS>1.6500</pPIS><vPIS>0.41</vPIS></PISAliq></PIS><COFINS><COFINSAliq><CST>01</CST><vBC>25.04</vBC><pCOFINS>7.6000</pCOFINS><vCOFINS>1.90</vCOFINS></COFINSAliq></COFINS></imposto><infAdProd>Resolu ao do Senado Federal n  13/12,N  da FCI 4625CA03-2835-4B02-9FBD-497330038B70</infAdProd></det><det nItem="4"><prod><cProd>000000000012304561</cProd><cEAN>7891000113608</cEAN><xProd>ESPECIALIDADES Bombons 30x300g BR</xProd><NCM>18069000</NCM><CEST>1700700</CEST><indEscala>S</indEscala><CFOP>5102</CFOP><uCom>UNI</uCom><qCom>10.0000</qCom><vUnCom>7.0270000000</vUnCom><vProd>70.27</vProd><cEANTrib>7891000113608</cEANTrib><uTrib>UNI</uTrib><qTrib>10.0000</qTrib><vUnTrib>7.0270000000</vUnTrib><indTot>1</indTot><xPed>1077651</xPed><nItemPed>000040</nItemPed><nFCI>4FBF89FA-A25D-45CB-8B68-5432B837C71E</nFCI></prod><imposto><ICMS><ICMS20><orig>5</orig><CST>20</CST><modBC>3</modBC><pRedBC>29.4100</pRedBC><vBC>49.60</vBC><pICMS>17.0000</pICMS><vICMS>8.43</vICMS></ICMS20></ICMS><IPI><cEnq>999</cEnq><IPITrib><CST>99</CST><vBC>0.00</vBC><pIPI>0.0000</pIPI><vIPI>0.00</vIPI></IPITrib></IPI><PIS><PISAliq><CST>01</CST><vBC>70.27</vBC><pPIS>1.6500</pPIS><vPIS>1.16</vPIS></PISAliq></PIS><COFINS><COFINSAliq><CST>01</CST><vBC>70.27</vBC><pCOFINS>7.6000</pCOFINS><vCOFINS>5.34</vCOFINS></COFINSAliq></COFINS></imposto><infAdProd>Resolu ao do Senado Federal n  13/12,N  da FCI 4FBF89FA-A25D-45CB-8B68-5432B837C71E</infAdProd></det><total><ICMSTot><vBC>106.32</vBC><vICMS>18.06</vICMS><vICMSDeson>0.00</vICMSDeson><vFCP>0.00</vFCP><vBCST>0.00</vBCST><vST>0.00</vST><vFCPST>0.00</vFCPST><vFCPSTRet>0.00</vFCPSTRet><vProd>150.61</vProd><vFrete>0.00</vFrete><vSeg>0.00</vSeg><vDesc>0.00</vDesc><vII>0.00</vII><vIPI>0.00</vIPI><vIPIDevol>0.00</vIPIDevol><vPIS>2.20</vPIS><vCOFINS>10.16</vCOFINS><vOutro>0.00</vOutro><vNF>150.61</vNF></ICMSTot></total><transp><modFrete>0</modFrete><transporta><CNPJ>22384244000158</CNPJ><xNome>Mana Broker e Logistica Ltda</xNome><IE>257638075</IE><xEnder>Avenida Leopoldo Sand 3514 Letra E</xEnder><xMun>Chapeco</xMun><UF>SC</UF></transporta><vol><qVol>18</qVol><esp>Diversos</esp><pesoL>6.123</pesoL><pesoB>6.650</pesoB></vol></transp><pag><detPag><tPag>15</tPag><vPag>150.61</vPag></detPag></pag><infAdic><infCpl>Docnum: 0107096588 Cli: 0002981023 FFt: 7206 Emp: BR10 Org. Vendas: BRL1 / 06 / 00 Fvd: Remessa: 8290601918 Doct.Fat: 9540439505 N. Carga: 8020683201 Parceiro 10221053 Pedido: 5303990701 *Boleto Anexo* TaxPerm 72.0000000 PedCli: 1077651 DISPENSA DA EMISSAO DO CTRC CONFORME ARTIGO 67 DO ANEXO 5 DO RICMS Vol(M3): 0.018Valor Liquido: 150,61Redu ao da base Placa Veiculo:QIM0952 UF:SC Reboque: UF:</infCpl><obsCont xCampo="FATURA"><xTexto>CondPagto Vencto14dias apos dtfatura Venc 170818</xTexto></obsCont></infAdic></infNFe><Signature xmlns="http://www.w3.org/2000/09/xmldsig#"><SignedInfo><CanonicalizationMethod Algorithm="http://www.w3.org/TR/2001/REC-xml-c14n-20010315" /><SignatureMethod Algorithm="http://www.w3.org/2000/09/xmldsig#rsa-sha1" /><Reference URI="#NFe42180860409075045253550010004211641288923571"><Transforms><Transform Algorithm="http://www.w3.org/2000/09/xmldsig#enveloped-signature" /><Transform Algorithm="http://www.w3.org/TR/2001/REC-xml-c14n-20010315" /></Transforms><DigestMethod Algorithm="http://www.w3.org/2000/09/xmldsig#sha1" /><DigestValue>GNTKqq6v3SFusVLEC/sVlQsQdS8=</DigestValue></Reference></SignedInfo><SignatureValue>KUPYxbBAJGzIVkOIYUqJ2uvC/cKTGZMANk/KhvdZ3TNAWs0VdoDy6iXFAqDlbTBZikB1A4SRI4O4
/4bO9uIlD1nqXHNHXgzAtGcawOtOEcskg0KV5ac4TEvDAWUMSP6Vh1a1lDegBpDZYx7jnExueZAM
BuULK+IgCBdkKnGh+hG8Lyee11xn77xjIHAXulSO3wLeZXG0ZSOj/rTi7dAcKiT6gcYyq/5jRN6E
a39khI9ReE9wMAYs0ORbwSRFmUVVPnpUyuS/Vzu0Y5qYzOdkJuMyJ94Kf1JyuGo5BZ5eNp7Xzvfq
zeOjWmO1r+bFBXLjqIN6re8cxrH7aHBsZtKwjQ==</SignatureValue><KeyInfo><X509Data><X509Certificate>MIIHrjCCBZagAwIBAgIQCvxkotGtU1hcO7ZMZYM2DTANBgkqhkiG9w0BAQsFADB0MQswCQYDVQQG
EwJCUjETMBEGA1UEChMKSUNQLUJyYXNpbDEtMCsGA1UECxMkQ2VydGlzaWduIENlcnRpZmljYWRv
cmEgRGlnaXRhbCBTLkEuMSEwHwYDVQQDExhBQyBDZXJ0aXNpZ24gTXVsdGlwbGEgRzcwHhcNMTgw
NDExMTkyNjEwWhcNMTkwNDExMTkyNjEwWjB8MQswCQYDVQQGEwJCUjETMBEGA1UECgwKSUNQLUJy
YXNpbDEeMBwGA1UECwwVQXV0ZW50aWNhZG8gcG9yIEFSIE0yMRswGQYDVQQLDBJBc3NpbmF0dXJh
IFRpcG8gQTExGzAZBgNVBAMMEk5FU1RMRSBCUkFTSUwgTFREQTCCASIwDQYJKoZIhvcNAQEBBQAD
ggEPADCCAQoCggEBAIVvn5pM9aOnffcG21stShwTAdgwahiMVM9G4c5MNWTtZ9XcR/PTgWtIv2I3
Yybur0sYg3h5RyvIs3wZ/8pcFh51gCAONzvMWES99KqEkPpBCOxCvoxM65KXZ3IF2vu/Eyqp8nIm
hJiOf1nFK1yVc7cqkaKuaJ5efbTfMYcEIWeqcokYXr3qTL18yOhRDEyXDmUlFmvC51ZZY7bJV+3i
2y4OaICZPnQXU2iL20DZhbwrte1FKGWPTsqptD77MvANgtFwPdJ6dSdr4fjZT4s6Qm9VlnIx//9p
XrIjgvzCBo6zWkcDECPBL+a3sIT063uqK7TX0GZAZUUZzCdg7jNfZ40CAwEAAaOCAzIwggMuMIHA
BgNVHREEgbgwgbWgOAYFYEwBAwSgLwQtMjEwODE5NjEwNDIyODYyNzg5NzAwMDAwMDAwMDAwMDAw
MDAwMDAwMDAwMDAwoCcGBWBMAQMCoB4EHEpPU0UgRkxBVklPIEFST1VDSEUgREUgU09VWkGgGQYF
YEwBAwOgEAQONjA0MDkwNzUwMDAxNTKgFwYFYEwBAwegDgQMMDAwMDAwMDAwMDAwgRxhZGVsaW5l
LmJhcnJvc0Bici5uZXN0bGUuY29tMAkGA1UdEwQCMAAwHwYDVR0jBBgwFoAUXXIMvzPSu+OGpuhM
BnF+VVwHoNYwgYsGA1UdIASBgzCBgDB+BgZgTAECAQswdDByBggrBgEFBQcCARZmaHR0cDovL2lj
cC1icmFzaWwuY2VydGlzaWduLmNvbS5ici9yZXBvc2l0b3Jpby9kcGMvQUNfQ2VydGlzaWduX011
bHRpcGxhL0RQQ19BQ19DZXJ0aVNpZ25fTXVsdGlwbGEucGRmMIHGBgNVHR8Egb4wgbswXKBaoFiG
Vmh0dHA6Ly9pY3AtYnJhc2lsLmNlcnRpc2lnbi5jb20uYnIvcmVwb3NpdG9yaW8vbGNyL0FDQ2Vy
dGlzaWduTXVsdGlwbGFHNy9MYXRlc3RDUkwuY3JsMFugWaBXhlVodHRwOi8vaWNwLWJyYXNpbC5v
dXRyYWxjci5jb20uYnIvcmVwb3NpdG9yaW8vbGNyL0FDQ2VydGlzaWduTXVsdGlwbGFHNy9MYXRl
c3RDUkwuY3JsMA4GA1UdDwEB/wQEAwIF4DAdBgNVHSUEFjAUBggrBgEFBQcDAgYIKwYBBQUHAwQw
gbYGCCsGAQUFBwEBBIGpMIGmMGQGCCsGAQUFBzAChlhodHRwOi8vaWNwLWJyYXNpbC5jZXJ0aXNp
Z24uY29tLmJyL3JlcG9zaXRvcmlvL2NlcnRpZmljYWRvcy9BQ19DZXJ0aXNpZ25fTXVsdGlwbGFf
RzcucDdjMD4GCCsGAQUFBzABhjJodHRwOi8vb2NzcC1hYy1jZXJ0aXNpZ24tbXVsdGlwbGEuY2Vy
dGlzaWduLmNvbS5icjANBgkqhkiG9w0BAQsFAAOCAgEAUboD7UCALKBFClWxFv2BtqFgPAhc5+bK
TeXrLgZagW65ns2XIG5i2egT3/sIHLHPfbF1CE2zCzF8YCB6w+bsqrwcXOmeCpqziTxJIKmntmpL
nCTnn5p01ODj2gIs3/LpCBUVounlAbp3v5jYTMxqTJ52TG2Oyvk84TRCWosK89Aq6keOaaBiTy54
joz0YL1BmVngZR2+Kz7kY3gmrSD64pnrXmQxrsG6/UP6dzA9Rf/LgN4CRmb3MZrrt8FcGUzYsN84
/qkUbILiZPiMIKgqRVJmUPknnAd9WPZ7mJASusCJBWYEwhsK39mOxkJVeE1SG+7l8LEjp+e9YGu+
9T8ILTKnDndPgZ0miBUUepD1yEbFOcw+sH/Idl9EPKjVQQS2wR7uln6SW1jfGpM5vV9z8y5Kq2Lo
XIyGeNH8x37JZJ4NFJmf3XipwiPx2QU+6CPHnUGp3AxP1DZlqXscxb5oaLmGZhP0cOYROFrXIyBi
VG1WdhN8cBLeYKVlRMMWW1tNma6DaB1CiKHAyxfgHeUGav0GgmFNBFHRdzGqqLuLt4ujvCaMblPe
qYqfuVQkR8bcwz0oVUR/9IIT6YP/xgJTbS8Bt+y3WjwbzAJj8Uyoriyat3dMjrKD5QKpSIxFYjlm
CkLVsk0CEC1t2tRxRStvGaW3Qx/jn/EjvmFNFsqlWoI=</X509Certificate></X509Data></KeyInfo></Signature></NFe><protNFe versao="4.00"><infProt Id="ID342180105186233"><tpAmb>1</tpAmb><verAplic>SVRS201808020730</verAplic><chNFe>42180860409075045253550010004211641288923571</chNFe><dhRecbto>2018-08-03T11:20:18-03:00</dhRecbto><nProt>342180105186233</nProt><digVal>GNTKqq6v3SFusVLEC/sVlQsQdS8=</digVal><cStat>100</cStat><xMotivo>Autorizado o uso da NF-e</xMotivo></infProt></protNFe></nfeProc>