<?xml version="1.0" encoding="UTF-8" ?><nfeProc versao="4.00" xmlns="http://www.portalfiscal.inf.br/nfe"><NFe xmlns="http://www.portalfiscal.inf.br/nfe"><infNFe Id="NFe42180760409075045253550010004167241011704130" versao="4.00"><ide><cUF>42</cUF><cNF>01170413</cNF><natOp>VDA.MERC.ADQ.REC.DE TERCEIROS</natOp><mod>55</mod><serie>1</serie><nNF>416724</nNF><dhEmi>2018-07-17T10:39:13-03:00</dhEmi><dhSaiEnt>2018-07-17T10:44:13-03:00</dhSaiEnt><tpNF>1</tpNF><idDest>1</idDest><cMunFG>4204202</cMunFG><tpImp>2</tpImp><tpEmis>1</tpEmis><cDV>0</cDV><tpAmb>1</tpAmb><finNFe>1</finNFe><indFinal>0</indFinal><indPres>9</indPres><procEmi>0</procEmi><verProc>SAP GRC NFE 4.00</verProc></ide><emit><CNPJ>60409075045253</CNPJ><xNome>Nestle Brasil Ltda</xNome><xFant>BR DC Broker ManA</xFant><enderEmit><xLgr>Av Leopoldo Sander</xLgr><nro>3514</nro><xCpl>LET E S1</xCpl><xBairro>Engenho Braun</xBairro><cMun>4204202</cMun><xMun>Chapeco</xMun><UF>SC</UF><CEP>89809300</CEP><xPais>Brasil</xPais><fone>4933307800</fone></enderEmit><IE>256899517</IE><CRT>3</CRT></emit><dest><CNPJ>79496808000161</CNPJ><xNome>Abastecedora Perizzolo Ltda</xNome><enderDest><xLgr>R Fernando Machado</xLgr><nro>1294d</nro><xBairro>Centro</xBairro><cMun>4204202</cMun><xMun>Chapeco</xMun><UF>SC</UF><CEP>89802111</CEP><cPais>1058</cPais><xPais>Brasil</xPais><fone>4933221047</fone></enderDest><indIEDest>1</indIEDest><IE>251375870</IE></dest><det nItem="1"><prod><cProd>000000000011320198</cProd><cEAN>7891008198027</cEAN><xProd>TALENTO Tab Leite Cast Para 18(15x25g)XW</xProd><NCM>18063210</NCM><CEST>1700300</CEST><indEscala>S</indEscala><CFOP>5102</CFOP><uCom>EXB</uCom><qCom>1.0000</qCom><vUnCom>22.2500000000</vUnCom><vProd>22.25</vProd><cEANTrib>78907478</cEANTrib><uTrib>UNI</uTrib><qTrib>15.0000</qTrib><vUnTrib>1.4833333333</vUnTrib><indTot>1</indTot><xPed>1064634</xPed><nItemPed>000010</nItemPed><nFCI>4E806C82-F03D-40C0-B5C8-408BBE5AF1D6</nFCI></prod><imposto><ICMS><ICMS20><orig>5</orig><CST>20</CST><modBC>3</modBC><pRedBC>29.4100</pRedBC><vBC>15.71</vBC><pICMS>17.0000</pICMS><vICMS>2.67</vICMS></ICMS20></ICMS><IPI><cEnq>999</cEnq><IPITrib><CST>99</CST><vBC>0.00</vBC><pIPI>0.0000</pIPI><vIPI>0.00</vIPI></IPITrib></IPI><PIS><PISAliq><CST>01</CST><vBC>22.25</vBC><pPIS>1.6500</pPIS><vPIS>0.37</vPIS></PISAliq></PIS><COFINS><COFINSAliq><CST>01</CST><vBC>22.25</vBC><pCOFINS>7.6000</pCOFINS><vCOFINS>1.69</vCOFINS></COFINSAliq></COFINS></imposto><infAdProd>Resolu ao do Senado Federal n  13/12,N  da FCI 4E806C82-F03D-40C0-B5C8-408BBE5AF1D6</infAdProd></det><det nItem="2"><prod><cProd>000000000011320199</cProd><cEAN>7891008199024</cEAN><xProd>TALENTO Tab Choc Bco Cer 18(15x25g) XW</xProd><NCM>17049010</NCM><CEST>1700100</CEST><indEscala>S</indEscala><CFOP>5102</CFOP><uCom>EXB</uCom><qCom>1.0000</qCom><vUnCom>22.2500000000</vUnCom><vProd>22.25</vProd><cEANTrib>78907485</cEANTrib><uTrib>UNI</uTrib><qTrib>15.0000</qTrib><vUnTrib>1.4833333333</vUnTrib><indTot>1</indTot><xPed>1064634</xPed><nItemPed>000020</nItemPed><nFCI>76F16443-EB2F-4C8A-B489-A892190CD8C6</nFCI></prod><imposto><ICMS><ICMS20><orig>5</orig><CST>20</CST><modBC>3</modBC><pRedBC>29.4100</pRedBC><vBC>15.71</vBC><pICMS>17.0000</pICMS><vICMS>2.67</vICMS></ICMS20></ICMS><IPI><cEnq>999</cEnq><IPITrib><CST>99</CST><vBC>0.00</vBC><pIPI>0.0000</pIPI><vIPI>0.00</vIPI></IPITrib></IPI><PIS><PISAliq><CST>01</CST><vBC>22.25</vBC><pPIS>1.6500</pPIS><vPIS>0.37</vPIS></PISAliq></PIS><COFINS><COFINSAliq><CST>01</CST><vBC>22.25</vBC><pCOFINS>7.6000</pCOFINS><vCOFINS>1.69</vCOFINS></COFINSAliq></COFINS></imposto><infAdProd>Resolu ao do Senado Federal n  13/12,N  da FCI 76F16443-EB2F-4C8A-B489-A892190CD8C6</infAdProd></det><det nItem="3"><prod><cProd>000000000011320209</cProd><cEAN>7891008209020</cEAN><xProd>TALENTO Tab Leite Avelas 18(15x25g) XW</xProd><NCM>18063210</NCM><CEST>1700300</CEST><indEscala>S</indEscala><CFOP>5102</CFOP><uCom>EXB</uCom><qCom>1.0000</qCom><vUnCom>22.2500000000</vUnCom><vProd>22.25</vProd><cEANTrib>78907461</cEANTrib><uTrib>UNI</uTrib><qTrib>15.0000</qTrib><vUnTrib>1.4833333333</vUnTrib><indTot>1</indTot><xPed>1064634</xPed><nItemPed>000030</nItemPed><nFCI>14337E43-3262-4E8B-9CEE-A1FDFB823DA9</nFCI></prod><imposto><ICMS><ICMS20><orig>5</orig><CST>20</CST><modBC>3</modBC><pRedBC>29.4100</pRedBC><vBC>15.71</vBC><pICMS>17.0000</pICMS><vICMS>2.67</vICMS></ICMS20></ICMS><IPI><cEnq>999</cEnq><IPITrib><CST>99</CST><vBC>0.00</vBC><pIPI>0.0000</pIPI><vIPI>0.00</vIPI></IPITrib></IPI><PIS><PISAliq><CST>01</CST><vBC>22.25</vBC><pPIS>1.6500</pPIS><vPIS>0.37</vPIS></PISAliq></PIS><COFINS><COFINSAliq><CST>01</CST><vBC>22.25</vBC><pCOFINS>7.6000</pCOFINS><vCOFINS>1.69</vCOFINS></COFINSAliq></COFINS></imposto><infAdProd>Resolu ao do Senado Federal n  13/12,N  da FCI 14337E43-3262-4E8B-9CEE-A1FDFB823DA9</infAdProd></det><det nItem="4"><prod><cProd>000000000012285127</cProd><cEAN>7891008251272</cEAN><xProd>TALENTO Tab Choc Branco Cer 8(12x90g) XW</xProd><NCM>17049010</NCM><CEST>1700100</CEST><indEscala>S</indEscala><CFOP>5102</CFOP><uCom>EXB</uCom><qCom>1.0000</qCom><vUnCom>46.0700000000</vUnCom><vProd>46.07</vProd><cEANTrib>7891008151275</cEANTrib><uTrib>UNI</uTrib><qTrib>12.0000</qTrib><vUnTrib>3.8391666667</vUnTrib><indTot>1</indTot><xPed>1064634</xPed><nItemPed>000040</nItemPed><nFCI>55379685-9314-4948-8B0F-1B12500FDBEC</nFCI></prod><imposto><ICMS><ICMS20><orig>5</orig><CST>20</CST><modBC>3</modBC><pRedBC>29.4100</pRedBC><vBC>32.52</vBC><pICMS>17.0000</pICMS><vICMS>5.53</vICMS></ICMS20></ICMS><IPI><cEnq>999</cEnq><IPITrib><CST>99</CST><vBC>0.00</vBC><pIPI>0.0000</pIPI><vIPI>0.00</vIPI></IPITrib></IPI><PIS><PISAliq><CST>01</CST><vBC>46.07</vBC><pPIS>1.6500</pPIS><vPIS>0.76</vPIS></PISAliq></PIS><COFINS><COFINSAliq><CST>01</CST><vBC>46.07</vBC><pCOFINS>7.6000</pCOFINS><vCOFINS>3.50</vCOFINS></COFINSAliq></COFINS></imposto><infAdProd>Resolu ao do Senado Federal n  13/12,N  da FCI 55379685-9314-4948-8B0F-1B12500FDBEC</infAdProd></det><det nItem="5"><prod><cProd>000000000012311892</cProd><cEAN>7891008218923</cEAN><xProd>TALENTO Tab Leite Avelas 8(12x90g) XW</xProd><NCM>18063210</NCM><CEST>1700300</CEST><indEscala>S</indEscala><CFOP>5102</CFOP><uCom>EXB</uCom><qCom>1.0000</qCom><vUnCom>46.0700000000</vUnCom><vProd>46.07</vProd><cEANTrib>7891008118926</cEANTrib><uTrib>UNI</uTrib><qTrib>12.0000</qTrib><vUnTrib>3.8391666667</vUnTrib><indTot>1</indTot><xPed>1064634</xPed><nItemPed>000050</nItemPed><nFCI>CEA0035B-3CD8-4CBE-AA52-0CE05E06EB6C</nFCI></prod><imposto><ICMS><ICMS20><orig>5</orig><CST>20</CST><modBC>3</modBC><pRedBC>29.4100</pRedBC><vBC>32.52</vBC><pICMS>17.0000</pICMS><vICMS>5.53</vICMS></ICMS20></ICMS><IPI><cEnq>999</cEnq><IPITrib><CST>99</CST><vBC>0.00</vBC><pIPI>0.0000</pIPI><vIPI>0.00</vIPI></IPITrib></IPI><PIS><PISAliq><CST>01</CST><vBC>46.07</vBC><pPIS>1.6500</pPIS><vPIS>0.76</vPIS></PISAliq></PIS><COFINS><COFINSAliq><CST>01</CST><vBC>46.07</vBC><pCOFINS>7.6000</pCOFINS><vCOFINS>3.50</vCOFINS></COFINSAliq></COFINS></imposto><infAdProd>Resolu ao do Senado Federal n  13/12,N  da FCI CEA0035B-3CD8-4CBE-AA52-0CE05E06EB6C</infAdProd></det><det nItem="6"><prod><cProd>000000000012312312</cProd><cEAN>7891008223125</cEAN><xProd>TALENTO Tab Leite Cast Para 8(12x90g) XW</xProd><NCM>18063210</NCM><CEST>1700300</CEST><indEscala>S</indEscala><CFOP>5102</CFOP><uCom>EXB</uCom><qCom>1.0000</qCom><vUnCom>46.0700000000</vUnCom><vProd>46.07</vProd><cEANTrib>7891008123128</cEANTrib><uTrib>UNI</uTrib><qTrib>12.0000</qTrib><vUnTrib>3.8391666667</vUnTrib><indTot>1</indTot><xPed>1064634</xPed><nItemPed>000060</nItemPed><nFCI>2AC3B1BF-24E4-4872-89A0-6D8B930395E1</nFCI></prod><imposto><ICMS><ICMS20><orig>5</orig><CST>20</CST><modBC>3</modBC><pRedBC>29.4100</pRedBC><vBC>32.52</vBC><pICMS>17.0000</pICMS><vICMS>5.53</vICMS></ICMS20></ICMS><IPI><cEnq>999</cEnq><IPITrib><CST>99</CST><vBC>0.00</vBC><pIPI>0.0000</pIPI><vIPI>0.00</vIPI></IPITrib></IPI><PIS><PISAliq><CST>01</CST><vBC>46.07</vBC><pPIS>1.6500</pPIS><vPIS>0.76</vPIS></PISAliq></PIS><COFINS><COFINSAliq><CST>01</CST><vBC>46.07</vBC><pCOFINS>7.6000</pCOFINS><vCOFINS>3.50</vCOFINS></COFINSAliq></COFINS></imposto><infAdProd>Resolu ao do Senado Federal n  13/12,N  da FCI 2AC3B1BF-24E4-4872-89A0-6D8B930395E1</infAdProd></det><det nItem="7"><prod><cProd>000000000012312330</cProd><cEAN>7891008223309</cEAN><xProd>TALENTO Tab Choc Amendoa Pas 8(12x90g)XW</xProd><NCM>18063210</NCM><CEST>1700300</CEST><indEscala>S</indEscala><CFOP>5102</CFOP><uCom>EXB</uCom><qCom>1.0000</qCom><vUnCom>46.0700000000</vUnCom><vProd>46.07</vProd><cEANTrib>7891008123302</cEANTrib><uTrib>UNI</uTrib><qTrib>12.0000</qTrib><vUnTrib>3.8391666667</vUnTrib><indTot>1</indTot><xPed>1064634</xPed><nItemPed>000070</nItemPed><nFCI>661EF22E-B0DD-4CF8-A216-D908966EAF02</nFCI></prod><imposto><ICMS><ICMS20><orig>5</orig><CST>20</CST><modBC>3</modBC><pRedBC>29.4100</pRedBC><vBC>32.52</vBC><pICMS>17.0000</pICMS><vICMS>5.53</vICMS></ICMS20></ICMS><IPI><cEnq>999</cEnq><IPITrib><CST>99</CST><vBC>0.00</vBC><pIPI>0.0000</pIPI><vIPI>0.00</vIPI></IPITrib></IPI><PIS><PISAliq><CST>01</CST><vBC>46.07</vBC><pPIS>1.6500</pPIS><vPIS>0.76</vPIS></PISAliq></PIS><COFINS><COFINSAliq><CST>01</CST><vBC>46.07</vBC><pCOFINS>7.6000</pCOFINS><vCOFINS>3.50</vCOFINS></COFINSAliq></COFINS></imposto><infAdProd>Resolu ao do Senado Federal n  13/12,N  da FCI 661EF22E-B0DD-4CF8-A216-D908966EAF02</infAdProd></det><det nItem="8"><prod><cProd>000000000012347059</cProd><cEAN>7891008270594</cEAN><xProd>TALENTO Tab Rech Cookies 8(12x90g) XW</xProd><NCM>18063110</NCM><CEST>1700200</CEST><indEscala>S</indEscala><CFOP>5102</CFOP><uCom>EXB</uCom><qCom>1.0000</qCom><vUnCom>46.0700000000</vUnCom><vProd>46.07</vProd><cEANTrib>7891008170597</cEANTrib><uTrib>UNI</uTrib><qTrib>12.0000</qTrib><vUnTrib>3.8391666667</vUnTrib><indTot>1</indTot><xPed>1064634</xPed><nItemPed>000080</nItemPed></prod><imposto><ICMS><ICMS20><orig>0</orig><CST>20</CST><modBC>3</modBC><pRedBC>29.4100</pRedBC><vBC>32.52</vBC><pICMS>17.0000</pICMS><vICMS>5.53</vICMS></ICMS20></ICMS><IPI><cEnq>999</cEnq><IPITrib><CST>99</CST><vBC>0.00</vBC><pIPI>0.0000</pIPI><vIPI>0.00</vIPI></IPITrib></IPI><PIS><PISAliq><CST>01</CST><vBC>46.07</vBC><pPIS>1.6500</pPIS><vPIS>0.76</vPIS></PISAliq></PIS><COFINS><COFINSAliq><CST>01</CST><vBC>46.07</vBC><pCOFINS>7.6000</pCOFINS><vCOFINS>3.50</vCOFINS></COFINSAliq></COFINS></imposto></det><det nItem="9"><prod><cProd>000000000011320367</cProd><cEAN>7891008367027</cEAN><xProd>BATON Bastao Choc Leite 32(30x16g)XW</xProd><NCM>18063210</NCM><CEST>1700300</CEST><indEscala>S</indEscala><CFOP>5102</CFOP><uCom>EXB</uCom><qCom>1.0000</qCom><vUnCom>17.0100000000</vUnCom><vProd>17.01</vProd><cEANTrib>78912359</cEANTrib><uTrib>UNI</uTrib><qTrib>30.0000</qTrib><vUnTrib>0.5670000000</vUnTrib><indTot>1</indTot><xPed>1064634</xPed><nItemPed>000090</nItemPed><nFCI>A0A357EF-8491-4BBC-8635-DFC6FD3A91E1</nFCI></prod><imposto><ICMS><ICMS20><orig>5</orig><CST>20</CST><modBC>3</modBC><pRedBC>29.4100</pRedBC><vBC>12.01</vBC><pICMS>17.0000</pICMS><vICMS>2.04</vICMS></ICMS20></ICMS><IPI><cEnq>999</cEnq><IPITrib><CST>99</CST><vBC>0.00</vBC><pIPI>0.0000</pIPI><vIPI>0.00</vIPI></IPITrib></IPI><PIS><PISAliq><CST>01</CST><vBC>17.01</vBC><pPIS>1.6500</pPIS><vPIS>0.28</vPIS></PISAliq></PIS><COFINS><COFINSAliq><CST>01</CST><vBC>17.01</vBC><pCOFINS>7.6000</pCOFINS><vCOFINS>1.29</vCOFINS></COFINSAliq></COFINS></imposto><infAdProd>Resolu ao do Senado Federal n  13/12,N  da FCI A0A357EF-8491-4BBC-8635-DFC6FD3A91E1</infAdProd></det><det nItem="10"><prod><cProd>000000000012368980</cProd><cEAN>7891008289800</cEAN><xProd>BATON Extra Milk 32(30x16g) XW</xProd><NCM>18063110</NCM><CEST>1700200</CEST><indEscala>S</indEscala><CFOP>5102</CFOP><uCom>EXB</uCom><qCom>1.0000</qCom><vUnCom>17.0100000000</vUnCom><vProd>17.01</vProd><cEANTrib>78939363</cEANTrib><uTrib>UNI</uTrib><qTrib>30.0000</qTrib><vUnTrib>0.5670000000</vUnTrib><indTot>1</indTot><xPed>1064634</xPed><nItemPed>000100</nItemPed></prod><imposto><ICMS><ICMS20><orig>0</orig><CST>20</CST><modBC>3</modBC><pRedBC>29.4100</pRedBC><vBC>12.01</vBC><pICMS>17.0000</pICMS><vICMS>2.04</vICMS></ICMS20></ICMS><IPI><cEnq>999</cEnq><IPITrib><CST>99</CST><vBC>0.00</vBC><pIPI>0.0000</pIPI><vIPI>0.00</vIPI></IPITrib></IPI><PIS><PISAliq><CST>01</CST><vBC>17.01</vBC><pPIS>1.6500</pPIS><vPIS>0.28</vPIS></PISAliq></PIS><COFINS><COFINSAliq><CST>01</CST><vBC>17.01</vBC><pCOFINS>7.6000</pCOFINS><vCOFINS>1.29</vCOFINS></COFINSAliq></COFINS></imposto></det><total><ICMSTot><vBC>233.75</vBC><vICMS>39.74</vICMS><vICMSDeson>0.00</vICMSDeson><vFCP>0.00</vFCP><vBCST>0.00</vBCST><vST>0.00</vST><vFCPST>0.00</vFCPST><vFCPSTRet>0.00</vFCPSTRet><vProd>331.12</vProd><vFrete>0.00</vFrete><vSeg>0.00</vSeg><vDesc>0.00</vDesc><vII>0.00</vII><vIPI>0.00</vIPI><vIPIDevol>0.00</vIPIDevol><vPIS>5.47</vPIS><vCOFINS>25.15</vCOFINS><vOutro>0.00</vOutro><vNF>331.12</vNF></ICMSTot></total><transp><modFrete>0</modFrete><transporta><CNPJ>22384244000158</CNPJ><xNome>Mana Broker e Logistica Ltda</xNome><IE>257638075</IE><xEnder>Avenida Leopoldo Sand 3514 Letra E</xEnder><xMun>Chapeco</xMun><UF>SC</UF></transporta><vol><qVol>10</qVol><esp>EXB</esp><pesoL>7.485</pesoL><pesoB>7.839</pesoB></vol></transp><pag><detPag><tPag>15</tPag><vPag>331.12</vPag></detPag></pag><infAdic><infCpl>Docnum: 0102668533 Cli: 0002981023 FFt: 7206 Emp: BR10 Org. Vendas: BRNC / 01 / 00 Fvd: Remessa: 8289008384 Doct.Fat: 9538693232 N. Carga: 8020595868 Parceiro 01106455 Pedido: 5302445017 *Boleto Anexo* TaxPerm 72.0000000 PedCli: 1064634 DISPENSA DA EMISSAO DO CTRC CONFORME ARTIGO 67 DO ANEXO 5 DO RICMS Vol(M3): 0.013Valor Liquido: 331,12Redu ao da base Placa Veiculo:QIM0952 UF:SC Reboque: UF:</infCpl><obsCont xCampo="FATURA"><xTexto>CondPagto Vencto14dias apos dtfatura Venc 310718</xTexto></obsCont></infAdic></infNFe><Signature xmlns="http://www.w3.org/2000/09/xmldsig#"><SignedInfo><CanonicalizationMethod Algorithm="http://www.w3.org/TR/2001/REC-xml-c14n-20010315" /><SignatureMethod Algorithm="http://www.w3.org/2000/09/xmldsig#rsa-sha1" /><Reference URI="#NFe42180760409075045253550010004167241011704130"><Transforms><Transform Algorithm="http://www.w3.org/2000/09/xmldsig#enveloped-signature" /><Transform Algorithm="http://www.w3.org/TR/2001/REC-xml-c14n-20010315" /></Transforms><DigestMethod Algorithm="http://www.w3.org/2000/09/xmldsig#sha1" /><DigestValue>VZU/qJPKro9nyYKbyLGmqjIUHTs=</DigestValue></Reference></SignedInfo><SignatureValue>VECttVPzO1FTQxSdLkST7wDEjsQxpXJlq7RPb1IjxMui8BEORcVoVtptHlNNGc4RYpxU86cBcp17
utGQvqeGIm47QO0WQhK5l+MTu8JqDf5/NDTYRHmiJvVu80py8nBE1L1Y5a9Kk3+/Yk9R8IWYJevX
8RJL5kq35vGt8oyyL3aKmUVFQLadxT9pJDvwsdFjdDa3GfU62KoqeYWM5xTBQ8j9hGYXOzm+39Xl
Oqld31AoBZ7pAR77fHAEQrPvhjciATmbRyVie8QuWSetpd0CkMgPlAZQfr8xgLYatIpBnoUhiK+7
lIAdGHq8g0pPwxeKVXXqYgVUhfNVGMg2qHKpFQ==</SignatureValue><KeyInfo><X509Data><X509Certificate>MIIHrjCCBZagAwIBAgIQCvxkotGtU1hcO7ZMZYM2DTANBgkqhkiG9w0BAQsFADB0MQswCQYDVQQG
EwJCUjETMBEGA1UEChMKSUNQLUJyYXNpbDEtMCsGA1UECxMkQ2VydGlzaWduIENlcnRpZmljYWRv
cmEgRGlnaXRhbCBTLkEuMSEwHwYDVQQDExhBQyBDZXJ0aXNpZ24gTXVsdGlwbGEgRzcwHhcNMTgw
NDExMTkyNjEwWhcNMTkwNDExMTkyNjEwWjB8MQswCQYDVQQGEwJCUjETMBEGA1UECgwKSUNQLUJy
YXNpbDEeMBwGA1UECwwVQXV0ZW50aWNhZG8gcG9yIEFSIE0yMRswGQYDVQQLDBJBc3NpbmF0dXJh
IFRpcG8gQTExGzAZBgNVBAMMEk5FU1RMRSBCUkFTSUwgTFREQTCCASIwDQYJKoZIhvcNAQEBBQAD
ggEPADCCAQoCggEBAIVvn5pM9aOnffcG21stShwTAdgwahiMVM9G4c5MNWTtZ9XcR/PTgWtIv2I3
Yybur0sYg3h5RyvIs3wZ/8pcFh51gCAONzvMWES99KqEkPpBCOxCvoxM65KXZ3IF2vu/Eyqp8nIm
hJiOf1nFK1yVc7cqkaKuaJ5efbTfMYcEIWeqcokYXr3qTL18yOhRDEyXDmUlFmvC51ZZY7bJV+3i
2y4OaICZPnQXU2iL20DZhbwrte1FKGWPTsqptD77MvANgtFwPdJ6dSdr4fjZT4s6Qm9VlnIx//9p
XrIjgvzCBo6zWkcDECPBL+a3sIT063uqK7TX0GZAZUUZzCdg7jNfZ40CAwEAAaOCAzIwggMuMIHA
BgNVHREEgbgwgbWgOAYFYEwBAwSgLwQtMjEwODE5NjEwNDIyODYyNzg5NzAwMDAwMDAwMDAwMDAw
MDAwMDAwMDAwMDAwoCcGBWBMAQMCoB4EHEpPU0UgRkxBVklPIEFST1VDSEUgREUgU09VWkGgGQYF
YEwBAwOgEAQONjA0MDkwNzUwMDAxNTKgFwYFYEwBAwegDgQMMDAwMDAwMDAwMDAwgRxhZGVsaW5l
LmJhcnJvc0Bici5uZXN0bGUuY29tMAkGA1UdEwQCMAAwHwYDVR0jBBgwFoAUXXIMvzPSu+OGpuhM
BnF+VVwHoNYwgYsGA1UdIASBgzCBgDB+BgZgTAECAQswdDByBggrBgEFBQcCARZmaHR0cDovL2lj
cC1icmFzaWwuY2VydGlzaWduLmNvbS5ici9yZXBvc2l0b3Jpby9kcGMvQUNfQ2VydGlzaWduX011
bHRpcGxhL0RQQ19BQ19DZXJ0aVNpZ25fTXVsdGlwbGEucGRmMIHGBgNVHR8Egb4wgbswXKBaoFiG
Vmh0dHA6Ly9pY3AtYnJhc2lsLmNlcnRpc2lnbi5jb20uYnIvcmVwb3NpdG9yaW8vbGNyL0FDQ2Vy
dGlzaWduTXVsdGlwbGFHNy9MYXRlc3RDUkwuY3JsMFugWaBXhlVodHRwOi8vaWNwLWJyYXNpbC5v
dXRyYWxjci5jb20uYnIvcmVwb3NpdG9yaW8vbGNyL0FDQ2VydGlzaWduTXVsdGlwbGFHNy9MYXRl
c3RDUkwuY3JsMA4GA1UdDwEB/wQEAwIF4DAdBgNVHSUEFjAUBggrBgEFBQcDAgYIKwYBBQUHAwQw
gbYGCCsGAQUFBwEBBIGpMIGmMGQGCCsGAQUFBzAChlhodHRwOi8vaWNwLWJyYXNpbC5jZXJ0aXNp
Z24uY29tLmJyL3JlcG9zaXRvcmlvL2NlcnRpZmljYWRvcy9BQ19DZXJ0aXNpZ25fTXVsdGlwbGFf
RzcucDdjMD4GCCsGAQUFBzABhjJodHRwOi8vb2NzcC1hYy1jZXJ0aXNpZ24tbXVsdGlwbGEuY2Vy
dGlzaWduLmNvbS5icjANBgkqhkiG9w0BAQsFAAOCAgEAUboD7UCALKBFClWxFv2BtqFgPAhc5+bK
TeXrLgZagW65ns2XIG5i2egT3/sIHLHPfbF1CE2zCzF8YCB6w+bsqrwcXOmeCpqziTxJIKmntmpL
nCTnn5p01ODj2gIs3/LpCBUVounlAbp3v5jYTMxqTJ52TG2Oyvk84TRCWosK89Aq6keOaaBiTy54
joz0YL1BmVngZR2+Kz7kY3gmrSD64pnrXmQxrsG6/UP6dzA9Rf/LgN4CRmb3MZrrt8FcGUzYsN84
/qkUbILiZPiMIKgqRVJmUPknnAd9WPZ7mJASusCJBWYEwhsK39mOxkJVeE1SG+7l8LEjp+e9YGu+
9T8ILTKnDndPgZ0miBUUepD1yEbFOcw+sH/Idl9EPKjVQQS2wR7uln6SW1jfGpM5vV9z8y5Kq2Lo
XIyGeNH8x37JZJ4NFJmf3XipwiPx2QU+6CPHnUGp3AxP1DZlqXscxb5oaLmGZhP0cOYROFrXIyBi
VG1WdhN8cBLeYKVlRMMWW1tNma6DaB1CiKHAyxfgHeUGav0GgmFNBFHRdzGqqLuLt4ujvCaMblPe
qYqfuVQkR8bcwz0oVUR/9IIT6YP/xgJTbS8Bt+y3WjwbzAJj8Uyoriyat3dMjrKD5QKpSIxFYjlm
CkLVsk0CEC1t2tRxRStvGaW3Qx/jn/EjvmFNFsqlWoI=</X509Certificate></X509Data></KeyInfo></Signature></NFe><protNFe versao="4.00"><infProt Id="ID342180096233896"><tpAmb>1</tpAmb><verAplic>SVRS201806141121</verAplic><chNFe>42180760409075045253550010004167241011704130</chNFe><dhRecbto>2018-07-17T10:40:24-03:00</dhRecbto><nProt>342180096233896</nProt><digVal>VZU/qJPKro9nyYKbyLGmqjIUHTs=</digVal><cStat>100</cStat><xMotivo>Autorizado o uso da NF-e</xMotivo></infProt></protNFe></nfeProc>