<?xml version="1.0" encoding="UTF-8" ?><nfeProc versao="4.00" xmlns="http://www.portalfiscal.inf.br/nfe"><NFe xmlns="http://www.portalfiscal.inf.br/nfe"><infNFe Id="NFe42200860409075045253550010006079971569249460" versao="4.00"><ide><cUF>42</cUF><cNF>56924946</cNF><natOp>VDA.MERC.ADQ.REC.DE TERCEIROS</natOp><mod>55</mod><serie>1</serie><nNF>607997</nNF><dhEmi>2020-08-06T08:27:49-03:00</dhEmi><dhSaiEnt>2020-08-06T08:32:49-03:00</dhSaiEnt><tpNF>1</tpNF><idDest>1</idDest><cMunFG>4204202</cMunFG><tpImp>2</tpImp><tpEmis>1</tpEmis><cDV>0</cDV><tpAmb>1</tpAmb><finNFe>1</finNFe><indFinal>0</indFinal><indPres>9</indPres><procEmi>0</procEmi><verProc>SAP GRC NFE 4.00</verProc></ide><emit><CNPJ>60409075045253</CNPJ><xNome>Nestle Brasil Ltda</xNome><xFant>BR DC Broker ManA</xFant><enderEmit><xLgr>AC Jose Rodolfo Travi KM 48</xLgr><nro>s/n</nro><xBairro>Interior Chapeco</xBairro><cMun>4204202</cMun><xMun>Chapeco</xMun><UF>SC</UF><CEP>89815295</CEP><xPais>Brasil</xPais><fone>4933307800</fone></enderEmit><IE>256899517</IE><IM>389413</IM><CRT>3</CRT></emit><dest><CNPJ>79496808000161</CNPJ><xNome>Abastecedora Perizzolo Ltda</xNome><enderDest><xLgr>R Fernando Machado</xLgr><nro>1294d</nro><xBairro>Centro</xBairro><cMun>4204202</cMun><xMun>Chapeco</xMun><UF>SC</UF><CEP>89802111</CEP><cPais>1058</cPais><xPais>Brasil</xPais><fone>4933221047</fone></enderDest><indIEDest>1</indIEDest><IE>251375870</IE></dest><autXML><CNPJ>19417473000117</CNPJ></autXML><det nItem="1"><prod><cProd>000000000000413288</cProd><cEAN>7891000006290</cEAN><xProd>NESCAFE Com Leite 12x330g N1 BR</xProd><NCM>21011190</NCM><CEST>1710700</CEST><indEscala>S</indEscala><CFOP>5102</CFOP><uCom>UNI</uCom><qCom>3.0000</qCom><vUnCom>9.1433333333</vUnCom><vProd>27.43</vProd><cEANTrib>7891000006290</cEANTrib><uTrib>UNI</uTrib><qTrib>3.0000</qTrib><vUnTrib>9.1433333333</vUnTrib><indTot>1</indTot><xPed>1618721</xPed><nItemPed>000010</nItemPed><nFCI>2E20A3B4-72BB-4180-B7D0-BCED370634B7</nFCI></prod><imposto><ICMS><ICMS00><orig>5</orig><CST>00</CST><modBC>3</modBC><vBC>27.43</vBC><pICMS>12.0000</pICMS><vICMS>3.29</vICMS></ICMS00></ICMS><IPI><cEnq>999</cEnq><IPINT><CST>51</CST></IPINT></IPI><PIS><PISNT><CST>06</CST></PISNT></PIS><COFINS><COFINSNT><CST>06</CST></COFINSNT></COFINS></imposto><infAdProd>Resolucao do Senado Federal no 13/12,No da FCI 2E20A3B4-72BB-4180-B7D0-BCED370634B7</infAdProd></det><det nItem="2"><prod><cProd>000000000000414602</cProd><cEAN>7891000460214</cEAN><xProd>PRESTIGIO Chocolate 30x33g BR</xProd><NCM>18069000</NCM><CEST>1700900</CEST><indEscala>S</indEscala><CFOP>5102</CFOP><uCom>EXB</uCom><qCom>1.0000</qCom><vUnCom>31.7800000000</vUnCom><vProd>31.78</vProd><cEANTrib>7891000460207</cEANTrib><uTrib>UNI</uTrib><qTrib>30.0000</qTrib><vUnTrib>1.0593333333</vUnTrib><indTot>1</indTot><xPed>1618721</xPed><nItemPed>000040</nItemPed><nFCI>E2E8B8D3-8693-4DAF-AE45-2DE04D9F2E83</nFCI></prod><imposto><ICMS><ICMS00><orig>5</orig><CST>00</CST><modBC>3</modBC><vBC>31.78</vBC><pICMS>12.0000</pICMS><vICMS>3.81</vICMS></ICMS00></ICMS><IPI><cEnq>999</cEnq><IPITrib><CST>99</CST><vBC>0.00</vBC><pIPI>0.0000</pIPI><vIPI>0.00</vIPI></IPITrib></IPI><PIS><PISAliq><CST>01</CST><vBC>31.78</vBC><pPIS>1.6500</pPIS><vPIS>0.52</vPIS></PISAliq></PIS><COFINS><COFINSAliq><CST>01</CST><vBC>31.78</vBC><pCOFINS>7.6000</pCOFINS><vCOFINS>2.42</vCOFINS></COFINSAliq></COFINS></imposto><infAdProd>Resolucao do Senado Federal no 13/12,No da FCI E2E8B8D3-8693-4DAF-AE45-2DE04D9F2E83</infAdProd></det><det nItem="3"><prod><cProd>000000000012045051</cProd><cEAN>7891000051436</cEAN><xProd>PASSATEMPO Biscoito Leite 54x150g BR</xProd><NCM>19053100</NCM><CEST>1705301</CEST><indEscala>S</indEscala><CFOP>5102</CFOP><uCom>UNI</uCom><qCom>3.0000</qCom><vUnCom>1.8666666667</vUnCom><vProd>5.60</vProd><cEANTrib>7891000051436</cEANTrib><uTrib>UNI</uTrib><qTrib>3.0000</qTrib><vUnTrib>1.8666666667</vUnTrib><indTot>1</indTot><xPed>1618721</xPed><nItemPed>000060</nItemPed><nFCI>09D05B1C-E9B5-41BC-AF22-63EC32C03802</nFCI></prod><imposto><ICMS><ICMS00><orig>5</orig><CST>00</CST><modBC>3</modBC><vBC>5.60</vBC><pICMS>12.0000</pICMS><vICMS>0.67</vICMS></ICMS00></ICMS><IPI><cEnq>999</cEnq><IPINT><CST>51</CST></IPINT></IPI><PIS><PISAliq><CST>01</CST><vBC>5.60</vBC><pPIS>1.6500</pPIS><vPIS>0.09</vPIS></PISAliq></PIS><COFINS><COFINSAliq><CST>01</CST><vBC>5.60</vBC><pCOFINS>7.6000</pCOFINS><vCOFINS>0.43</vCOFINS></COFINSAliq></COFINS></imposto><infAdProd>Resolucao do Senado Federal no 13/12,No da FCI 09D05B1C-E9B5-41BC-AF22-63EC32C03802</infAdProd></det><det nItem="4"><prod><cProd>000000000012242943</cProd><cEAN>7891000101926</cEAN><xProd>NESCAU Bebida Garrafa Plas 4(6x270ml) BR</xProd><NCM>22029900</NCM><CEST>1711500</CEST><indEscala>S</indEscala><EXTIPI>01</EXTIPI><CFOP>5102</CFOP><uCom>UNI</uCom><qCom>12.0000</qCom><vUnCom>3.2408333333</vUnCom><vProd>38.89</vProd><cEANTrib>7891000101926</cEANTrib><uTrib>UNI</uTrib><qTrib>12.0000</qTrib><vUnTrib>3.2408333333</vUnTrib><indTot>1</indTot><xPed>1618721</xPed><nItemPed>000080</nItemPed><nFCI>A1198C9F-3B21-4F73-AB48-E1B78581E106</nFCI></prod><imposto><ICMS><ICMS00><orig>5</orig><CST>00</CST><modBC>3</modBC><vBC>38.89</vBC><pICMS>12.0000</pICMS><vICMS>4.67</vICMS></ICMS00></ICMS><IPI><cEnq>999</cEnq><IPINT><CST>51</CST></IPINT></IPI><PIS><PISNT><CST>06</CST></PISNT></PIS><COFINS><COFINSNT><CST>06</CST></COFINSNT></COFINS></imposto><infAdProd>Resolucao do Senado Federal no 13/12,No da FCI A1198C9F-3B21-4F73-AB48-E1B78581E106</infAdProd></det><det nItem="5"><prod><cProd>000000000012272048</cProd><cEAN>7891000107645</cEAN><xProd>ALPINO Chocolate Leite 12(18x25g) BR</xProd><NCM>18063210</NCM><CEST>1700300</CEST><indEscala>S</indEscala><CFOP>5102</CFOP><uCom>EXB</uCom><qCom>1.0000</qCom><vUnCom>19.8200000000</vUnCom><vProd>19.82</vProd><cEANTrib>7891000107638</cEANTrib><uTrib>UNI</uTrib><qTrib>18.0000</qTrib><vUnTrib>1.1011111111</vUnTrib><indTot>1</indTot><xPed>1618721</xPed><nItemPed>000090</nItemPed><nFCI>4625CA03-2835-4B02-9FBD-497330038B70</nFCI></prod><imposto><ICMS><ICMS00><orig>5</orig><CST>00</CST><modBC>3</modBC><vBC>19.82</vBC><pICMS>12.0000</pICMS><vICMS>2.38</vICMS></ICMS00></ICMS><IPI><cEnq>999</cEnq><IPITrib><CST>99</CST><vBC>0.00</vBC><pIPI>0.0000</pIPI><vIPI>0.00</vIPI></IPITrib></IPI><PIS><PISAliq><CST>01</CST><vBC>19.82</vBC><pPIS>1.6500</pPIS><vPIS>0.33</vPIS></PISAliq></PIS><COFINS><COFINSAliq><CST>01</CST><vBC>19.82</vBC><pCOFINS>7.6000</pCOFINS><vCOFINS>1.51</vCOFINS></COFINSAliq></COFINS></imposto><infAdProd>Resolucao do Senado Federal no 13/12,No da FCI 4625CA03-2835-4B02-9FBD-497330038B70</infAdProd></det><det nItem="6"><prod><cProd>000000000012272482</cProd><cEAN>7891000107843</cEAN><xProd>SUFLAIR Chocolate Leite 12(20x50g) BR</xProd><NCM>18063210</NCM><CEST>1700300</CEST><indEscala>S</indEscala><CFOP>5102</CFOP><uCom>EXB</uCom><qCom>1.0000</qCom><vUnCom>45.1000000000</vUnCom><vProd>45.10</vProd><cEANTrib>7891000107836</cEANTrib><uTrib>UNI</uTrib><qTrib>20.0000</qTrib><vUnTrib>2.2550000000</vUnTrib><indTot>1</indTot><xPed>1618721</xPed><nItemPed>000100</nItemPed><nFCI>9AC7D43E-000F-4F85-8F35-5B7273B10281</nFCI></prod><imposto><ICMS><ICMS00><orig>5</orig><CST>00</CST><modBC>3</modBC><vBC>45.10</vBC><pICMS>12.0000</pICMS><vICMS>5.41</vICMS></ICMS00></ICMS><IPI><cEnq>999</cEnq><IPITrib><CST>99</CST><vBC>0.00</vBC><pIPI>0.0000</pIPI><vIPI>0.00</vIPI></IPITrib></IPI><PIS><PISAliq><CST>01</CST><vBC>45.10</vBC><pPIS>1.6500</pPIS><vPIS>0.74</vPIS></PISAliq></PIS><COFINS><COFINSAliq><CST>01</CST><vBC>45.10</vBC><pCOFINS>7.6000</pCOFINS><vCOFINS>3.43</vCOFINS></COFINSAliq></COFINS></imposto><infAdProd>Resolucao do Senado Federal no 13/12,No da FCI 9AC7D43E-000F-4F85-8F35-5B7273B10281</infAdProd></det><det nItem="7"><prod><cProd>000000000012342557</cProd><cEAN>7891000248775</cEAN><xProd>KIT KAT 4Fngr Leite 4(24x41.5g) BR</xProd><NCM>19053200</NCM><CEST>1705800</CEST><indEscala>S</indEscala><CFOP>5102</CFOP><uCom>EXB</uCom><qCom>1.0000</qCom><vUnCom>45.4800000000</vUnCom><vProd>45.48</vProd><cEANTrib>7891000248768</cEANTrib><uTrib>UNI</uTrib><qTrib>24.0000</qTrib><vUnTrib>1.8950000000</vUnTrib><indTot>1</indTot><xPed>1618721</xPed><nItemPed>000110</nItemPed><nFCI>036EAD6E-96A7-4467-8A74-A49E4FB9C5AA</nFCI></prod><imposto><ICMS><ICMS00><orig>5</orig><CST>00</CST><modBC>3</modBC><vBC>45.48</vBC><pICMS>12.0000</pICMS><vICMS>5.46</vICMS></ICMS00></ICMS><IPI><cEnq>999</cEnq><IPINT><CST>51</CST></IPINT></IPI><PIS><PISAliq><CST>01</CST><vBC>45.48</vBC><pPIS>1.6500</pPIS><vPIS>0.75</vPIS></PISAliq></PIS><COFINS><COFINSAliq><CST>01</CST><vBC>45.48</vBC><pCOFINS>7.6000</pCOFINS><vCOFINS>3.46</vCOFINS></COFINSAliq></COFINS></imposto><infAdProd>Resolucao do Senado Federal no 13/12,No da FCI 036EAD6E-96A7-4467-8A74-A49E4FB9C5AA</infAdProd></det><det nItem="8"><prod><cProd>000000000012396173</cProd><cEAN>7891000276488</cEAN><xProd>ALPINO Chocolate 4(14x90g) BR</xProd><NCM>18063210</NCM><CEST>1700300</CEST><indEscala>S</indEscala><CFOP>5102</CFOP><uCom>EXB</uCom><qCom>1.0000</qCom><vUnCom>59.3800000000</vUnCom><vProd>59.38</vProd><cEANTrib>7891000276471</cEANTrib><uTrib>UNI</uTrib><qTrib>14.0000</qTrib><vUnTrib>4.2414285714</vUnTrib><indTot>1</indTot><xPed>1618721</xPed><nItemPed>000120</nItemPed><nFCI>B0D566A9-46F2-47B6-BA17-361F54D6CE04</nFCI></prod><imposto><ICMS><ICMS00><orig>5</orig><CST>00</CST><modBC>3</modBC><vBC>59.38</vBC><pICMS>12.0000</pICMS><vICMS>7.13</vICMS></ICMS00></ICMS><IPI><cEnq>999</cEnq><IPITrib><CST>99</CST><vBC>0.00</vBC><pIPI>0.0000</pIPI><vIPI>0.00</vIPI></IPITrib></IPI><PIS><PISAliq><CST>01</CST><vBC>59.38</vBC><pPIS>1.6500</pPIS><vPIS>0.98</vPIS></PISAliq></PIS><COFINS><COFINSAliq><CST>01</CST><vBC>59.38</vBC><pCOFINS>7.6000</pCOFINS><vCOFINS>4.51</vCOFINS></COFINSAliq></COFINS></imposto><infAdProd>Resolucao do Senado Federal no 13/12,No da FCI B0D566A9-46F2-47B6-BA17-361F54D6CE04</infAdProd></det><det nItem="9"><prod><cProd>000000000012396270</cProd><cEAN>7891000276846</cEAN><xProd>CLASSIC Duo Chocolate 4(14x90g) BR</xProd><NCM>18063210</NCM><CEST>1700300</CEST><indEscala>S</indEscala><CFOP>5102</CFOP><uCom>EXB</uCom><qCom>1.0000</qCom><vUnCom>59.3800000000</vUnCom><vProd>59.38</vProd><cEANTrib>7891000276839</cEANTrib><uTrib>UNI</uTrib><qTrib>14.0000</qTrib><vUnTrib>4.2414285714</vUnTrib><indTot>1</indTot><xPed>1618721</xPed><nItemPed>000130</nItemPed><nFCI>42E4E4BB-F563-4C78-B224-600865E50C58</nFCI></prod><imposto><ICMS><ICMS00><orig>5</orig><CST>00</CST><modBC>3</modBC><vBC>59.38</vBC><pICMS>12.0000</pICMS><vICMS>7.13</vICMS></ICMS00></ICMS><IPI><cEnq>999</cEnq><IPITrib><CST>99</CST><vBC>0.00</vBC><pIPI>0.0000</pIPI><vIPI>0.00</vIPI></IPITrib></IPI><PIS><PISAliq><CST>01</CST><vBC>59.38</vBC><pPIS>1.6500</pPIS><vPIS>0.98</vPIS></PISAliq></PIS><COFINS><COFINSAliq><CST>01</CST><vBC>59.38</vBC><pCOFINS>7.6000</pCOFINS><vCOFINS>4.51</vCOFINS></COFINSAliq></COFINS></imposto><infAdProd>Resolucao do Senado Federal no 13/12,No da FCI 42E4E4BB-F563-4C78-B224-600865E50C58</infAdProd></det><det nItem="10"><prod><cProd>000000000012439788</cProd><cEAN>7891000305232</cEAN><xProd>BONO Bisc Recheado Chocolate 60x126g BR</xProd><NCM>19053100</NCM><CEST>1705300</CEST><indEscala>S</indEscala><CFOP>5102</CFOP><uCom>UNI</uCom><qCom>3.0000</qCom><vUnCom>1.8766666667</vUnCom><vProd>5.63</vProd><cEANTrib>7891000305232</cEANTrib><uTrib>UNI</uTrib><qTrib>3.0000</qTrib><vUnTrib>1.8766666667</vUnTrib><indTot>1</indTot><xPed>1618721</xPed><nItemPed>000140</nItemPed></prod><imposto><ICMS><ICMS00><orig>0</orig><CST>00</CST><modBC>3</modBC><vBC>5.63</vBC><pICMS>12.0000</pICMS><vICMS>0.68</vICMS></ICMS00></ICMS><IPI><cEnq>999</cEnq><IPINT><CST>51</CST></IPINT></IPI><PIS><PISAliq><CST>01</CST><vBC>5.63</vBC><pPIS>1.6500</pPIS><vPIS>0.09</vPIS></PISAliq></PIS><COFINS><COFINSAliq><CST>01</CST><vBC>5.63</vBC><pCOFINS>7.6000</pCOFINS><vCOFINS>0.43</vCOFINS></COFINSAliq></COFINS></imposto></det><total><ICMSTot><vBC>338.49</vBC><vICMS>40.63</vICMS><vICMSDeson>0.00</vICMSDeson><vFCP>0.00</vFCP><vBCST>0.00</vBCST><vST>0.00</vST><vFCPST>0.00</vFCPST><vFCPSTRet>0.00</vFCPSTRet><vProd>338.49</vProd><vFrete>0.00</vFrete><vSeg>0.00</vSeg><vDesc>0.00</vDesc><vII>0.00</vII><vIPI>0.00</vIPI><vIPIDevol>0.00</vIPIDevol><vPIS>4.48</vPIS><vCOFINS>20.70</vCOFINS><vOutro>0.00</vOutro><vNF>338.49</vNF></ICMSTot></total><transp><modFrete>0</modFrete><transporta><CNPJ>22384244000158</CNPJ><xNome>Mana Broker e Logistica Ltda</xNome><IE>257638075</IE><xEnder>Ac Jose Rodolfo Travi SN</xEnder><xMun>Chapeco</xMun><UF>SC</UF></transporta><vol><qVol>27</qVol><esp>Diversos</esp><pesoL>11.146</pesoL><pesoB>12.085</pesoB></vol></transp><cobr><fat><nFat>9609160306</nFat><vOrig>338.49</vOrig><vDesc>0.00</vDesc><vLiq>338.49</vLiq></fat><dup><nDup>001</nDup><dVenc>2020-08-13</dVenc><vDup>338.49</vDup></dup></cobr><pag><detPag><tPag>15</tPag><vPag>338.49</vPag></detPag></pag><infAdic><infCpl>Docnum: 0145561652 Cli: 0002981023 FFt: 7206 Emp: BR10 Org. Vendas: BRL1 / 06 / 00 Fvd: Remessa: 8355150726 Doct.Fat: 9609160306 N. Carga: 8024101496 Parceiro 10981894 Pedido: 5366088651 *Boleto Anexo* Tax Perm 72.0000000 PedCli: 1618721 DISPENSA DA EMISS O DO CTRC CONFORME ARTIGO 67 DO ANEXO 5 DO RICMS Vol(M3): 0.027Valor L quido: 338,49 Placa Veiculo:QIM0952 UF:SC Reboque: UF:</infCpl><obsCont xCampo="FATURA"><xTexto>CondPagto Vencto7 dias apos data fatura Venc 130820</xTexto></obsCont></infAdic><infRespTec><CNPJ>60409075000152</CNPJ><xContato>Nestle Brasil LTDA</xContato><email>responsavel.tecnico@br.nestle.com</email><fone>00001155084400</fone></infRespTec></infNFe><Signature xmlns="http://www.w3.org/2000/09/xmldsig#"><SignedInfo><CanonicalizationMethod Algorithm="http://www.w3.org/TR/2001/REC-xml-c14n-20010315" /><SignatureMethod Algorithm="http://www.w3.org/2000/09/xmldsig#rsa-sha1" /><Reference URI="#NFe42200860409075045253550010006079971569249460"><Transforms><Transform Algorithm="http://www.w3.org/2000/09/xmldsig#enveloped-signature" /><Transform Algorithm="http://www.w3.org/TR/2001/REC-xml-c14n-20010315" /></Transforms><DigestMethod Algorithm="http://www.w3.org/2000/09/xmldsig#sha1" /><DigestValue>dE4yAHwq71ZVFuXCsXJbOim5YkQ=</DigestValue></Reference></SignedInfo><SignatureValue>fwggkqfzJrGbeA5XXZqox0qx0NVLphKGKliDP872Ys0opkK7GiEPtm/dsto1gN5rLU/D2fRyjnVS
DXFiVLKydbHgXlpvZ29e3D5U8mC8Xws+WOQ4vCTnIj9XmO4YIHeGWZYalwbQZepkY7VvBsTgXnUE
Q0IlU6Soc2atSZuUOTKalf/A2MnoImO3XAygl/eWDN+QyLaVuafvn3bvxKx4OlLD7knPw63Fp3oD
O6AVpq92dkpf0WT7VEqIursQrr/7kvh5pGVEBgLmLzVBaUnoA0tZzAAaQXVIn3AZxfMVaTq2RosE
lwwcPbRVs2wkZ/iRPJ1ek4B0B2U2gcd0eN/dXQ==</SignatureValue><KeyInfo><X509Data><X509Certificate>MIIH6jCCBdKgAwIBAgIQKzZKYCTAnamffjNA8M/U5zANBgkqhkiG9w0BAQsFADB4MQswCQYDVQQG
EwJCUjETMBEGA1UEChMKSUNQLUJyYXNpbDE2MDQGA1UECxMtU2VjcmV0YXJpYSBkYSBSZWNlaXRh
IEZlZGVyYWwgZG8gQnJhc2lsIC0gUkZCMRwwGgYDVQQDExNBQyBDZXJ0aXNpZ24gUkZCIEc1MB4X
DTE5MDgyMTE3NDA0MVoXDTIwMDgyMDE3NDA0MVowgdgxCzAJBgNVBAYTAkJSMRMwEQYDVQQKDApJ
Q1AtQnJhc2lsMQswCQYDVQQIDAJTUDESMBAGA1UEBwwJU2FvIFBhdWxvMTYwNAYDVQQLDC1TZWNy
ZXRhcmlhIGRhIFJlY2VpdGEgRmVkZXJhbCBkbyBCcmFzaWwgLSBSRkIxFjAUBgNVBAsMDVJGQiBl
LUNOUEogQTExFzAVBgNVBAsMDjAyMTcyOTgxMDAwMTgwMSowKAYDVQQDDCFORVNUTEUgQlJBU0lM
IExUREE6NjA0MDkwNzUwMDAxNTIwggEiMA0GCSqGSIb3DQEBAQUAA4IBDwAwggEKAoIBAQCbPLFs
KnBZsWZ0IxH/hP837GmKgcEU/CIm9a9qRgtjCzMOhCepdTUiUikw6KGAfeI0rPU4/D+IUVmyRy+F
Q78MBpyJNM05zIall5rqcwChU8fLf1IC3TlZqMMHReDzI7SSX5xPcOXCkgUpebkqIRfkVxltoaFA
c6mk54k1q/YrT6A77BqCCIz5EMn5Mo7t/QROBmIxLCVwwWA/EbduYkpcIE9Er1P1/8hlMtmv7Y0z
EYCbtB7yTB++/YcKxY3YBDnXVCXtPJpqvf//5TUYiWIn2V9tqLz1gIqc1ryUVjfvYIGi6JAC93J6
HyBqwQKCyCEzkCN3Oad4NfCAL1wYNPrRAgMBAAGjggMNMIIDCTCBvAYDVR0RBIG0MIGxoDgGBWBM
AQMEoC8ELTEzMDgxOTU5MjQyMTM1MjQ4NzYwMDAwMDAwMDAwMDAwMDAwMDAwMDAwMDAwMKAjBgVg
TAEDAqAaBBhNSUdVRUwgQU5HRUwgRElBWiBWQVJHQVOgGQYFYEwBAwOgEAQONjA0MDkwNzUwMDAx
NTKgFwYFYEwBAwegDgQMMDAwMDAwMDAwMDAwgRxnZW9yZ2lhLm1lbmRlc0Bici5uZXN0bGUuY29t
MAkGA1UdEwQCMAAwHwYDVR0jBBgwFoAUU31/nb7RYdAgutqf44mnE3NYzUIwfwYDVR0gBHgwdjB0
BgZgTAECAQwwajBoBggrBgEFBQcCARZcaHR0cDovL2ljcC1icmFzaWwuY2VydGlzaWduLmNvbS5i
ci9yZXBvc2l0b3Jpby9kcGMvQUNfQ2VydGlzaWduX1JGQi9EUENfQUNfQ2VydGlzaWduX1JGQi5w
ZGYwgbwGA1UdHwSBtDCBsTBXoFWgU4ZRaHR0cDovL2ljcC1icmFzaWwuY2VydGlzaWduLmNvbS5i
ci9yZXBvc2l0b3Jpby9sY3IvQUNDZXJ0aXNpZ25SRkJHNS9MYXRlc3RDUkwuY3JsMFagVKBShlBo
dHRwOi8vaWNwLWJyYXNpbC5vdXRyYWxjci5jb20uYnIvcmVwb3NpdG9yaW8vbGNyL0FDQ2VydGlz
aWduUkZCRzUvTGF0ZXN0Q1JMLmNybDAOBgNVHQ8BAf8EBAMCBeAwHQYDVR0lBBYwFAYIKwYBBQUH
AwIGCCsGAQUFBwMEMIGsBggrBgEFBQcBAQSBnzCBnDBfBggrBgEFBQcwAoZTaHR0cDovL2ljcC1i
cmFzaWwuY2VydGlzaWduLmNvbS5ici9yZXBvc2l0b3Jpby9jZXJ0aWZpY2Fkb3MvQUNfQ2VydGlz
aWduX1JGQl9HNS5wN2MwOQYIKwYBBQUHMAGGLWh0dHA6Ly9vY3NwLWFjLWNlcnRpc2lnbi1yZmIu
Y2VydGlzaWduLmNvbS5icjANBgkqhkiG9w0BAQsFAAOCAgEAsA8yRKv4LN+xdeQu6+Mh2U+j5kBj
iV6SGxp4OUV3iZwAsXAnmCipC4S3N+uue5Hubdab1wD69gy1qDIqAR4bXLc2q5b1wQjNKZlJn62F
2fEgLXnedT4fXW4NLkEobnc9NFj8tN/oiqyoCkW2QHABU2OX/AlVqYaHPIA169MT+x9yKZxH01Rk
E8b9XE+Ix2n7AXqAarwEberNX+8VHNLsRtjl2//OnPrUEFSwPSStpcnJn+C4X5njXZThI1dnbrKt
jzm3pwGqBMIIwzL1EY8/ZbYn5ho6aV9HgirdnCZlqtp0tude1XhGriw+PBLobzyXlScGDk+qQ/Ix
HBMI7SDDdXSnIZOG1NGIOwvbfeI6OEd/3jQVgZ+syz9ijyBdRFTJ4kbZxb9SEWN/1ZmX65fu6a6e
IKDoKB4+p8pYewXpVozeTWEtu5u/yZMxTE0u3foJCnIr1iT/4BvOPDeUjXopdP3BOgrAUxCaNCxT
SDrVaQES5q6Vpw+Tjmnf38ZytBFN6EiLW9keISjoUTn8EdHHReocM9KNsCmeMdQ1lSJ5VOUOPOmM
GT3x+n9auLpDvjdYRNbaRAfNrvpxpXLrdjWNK8YfcvTA4tFm0SXq14AXoyVLIjYmMrlcx5tFu1uA
XllXZiznDVcge5tEqfApa5cIscYh1nhtVji2eW1ypBM5biE=</X509Certificate></X509Data></KeyInfo></Signature></NFe><protNFe versao="4.00"><infProt Id="ID342200119039036"><tpAmb>1</tpAmb><verAplic>SVRS202006041529</verAplic><chNFe>42200860409075045253550010006079971569249460</chNFe><dhRecbto>2020-08-06T08:37:32-03:00</dhRecbto><nProt>342200119039036</nProt><digVal>dE4yAHwq71ZVFuXCsXJbOim5YkQ=</digVal><cStat>100</cStat><xMotivo>Autorizado o uso da NF-e</xMotivo></infProt></protNFe></nfeProc>