<?xml version="1.0" encoding="UTF-8" ?><nfeProc versao="4.00" xmlns="http://www.portalfiscal.inf.br/nfe"><NFe xmlns="http://www.portalfiscal.inf.br/nfe"><infNFe Id="NFe42190877887412000110550060003170911000211396" versao="4.00"><ide><cUF>42</cUF><cNF>00021139</cNF><natOp>VENDA DE MERCADORIA ADQUIRIDA OU RECEB.DE TERCEIRO</natOp><mod>55</mod><serie>6</serie><nNF>317091</nNF><dhEmi>2019-08-20T19:18:18-02:00</dhEmi><dhSaiEnt>2019-08-20T19:18:18-02:00</dhSaiEnt><tpNF>1</tpNF><idDest>1</idDest><cMunFG>4209003</cMunFG><tpImp>2</tpImp><tpEmis>1</tpEmis><cDV>6</cDV><tpAmb>1</tpAmb><finNFe>1</finNFe><indFinal>0</indFinal><indPres>9</indPres><procEmi>0</procEmi><verProc>5.5.1.3</verProc></ide><emit><CNPJ>77887412000110</CNPJ><xNome>DEYCON COMERCIO E DISTRIBUICAO LTDA</xNome><xFant>DEYCON JBA</xFant><enderEmit><xLgr>AV ADOLFO ZIGUELLI, 1021</xLgr><nro>.</nro><xBairro>CENTRO</xBairro><cMun>4209003</cMun><xMun>JOACABA</xMun><UF>SC</UF><CEP>89600000</CEP><fone>4935518700</fone></enderEmit><IE>251031942</IE><CRT>3</CRT></emit><dest><CNPJ>79496808000161</CNPJ><xNome>ABAST PERIZZOLO LTDA</xNome><enderDest><xLgr>AVEN FERNANDO MACHADO - D</xLgr><nro>1294</nro><xBairro>CENTRO</xBairro><cMun>4204202</cMun><xMun>CHAPECO</xMun><UF>SC</UF><CEP>89802111</CEP><fone>4933221047</fone></enderDest><indIEDest>1</indIEDest><IE>251375870</IE></dest><autXML><CNPJ>15470523000179</CNPJ></autXML><det nItem="1"><prod><cProd>7891079013038</cProd><cEAN>7891079013038</cEAN><xProd>491187-CUP NOODLES GALINHA CAIPIRA    NISSIN            03X69</xProd><NCM>19023000</NCM><CEST>1704700</CEST><indEscala>S</indEscala><CFOP>5102</CFOP><uCom>DP3</uCom><qCom>2.0000</qCom><vUnCom>7.7700</vUnCom><vProd>15.54</vProd><cEANTrib>7891079013038</cEANTrib><uTrib>UNID</uTrib><qTrib>6.0000</qTrib><vUnTrib>2.5900000001</vUnTrib><vOutro>0.11</vOutro><indTot>1</indTot></prod><imposto><vTotTrib>1.10</vTotTrib><ICMS><ICMS20><orig>0</orig><CST>20</CST><modBC>3</modBC><pRedBC>41.66</pRedBC><vBC>9.13</vBC><pICMS>12.00</pICMS><vICMS>1.10</vICMS></ICMS20></ICMS><PIS><PISNT><CST>06</CST></PISNT></PIS><COFINS><COFINSNT><CST>06</CST></COFINSNT></COFINS></imposto></det><det nItem="2"><prod><cProd>7891079013052</cProd><cEAN>7891079013052</cEAN><xProd>491188-CUP NOODLES CARNE DEFUMADA     NISSIN            03X69</xProd><NCM>19023000</NCM><CEST>1704700</CEST><indEscala>S</indEscala><CFOP>5102</CFOP><uCom>DP3</uCom><qCom>2.0000</qCom><vUnCom>7.7700</vUnCom><vProd>15.54</vProd><cEANTrib>7891079013052</cEANTrib><uTrib>UNID</uTrib><qTrib>6.0000</qTrib><vUnTrib>2.5900000001</vUnTrib><vOutro>0.11</vOutro><indTot>1</indTot></prod><imposto><vTotTrib>1.10</vTotTrib><ICMS><ICMS20><orig>0</orig><CST>20</CST><modBC>3</modBC><pRedBC>41.66</pRedBC><vBC>9.13</vBC><pICMS>12.00</pICMS><vICMS>1.10</vICMS></ICMS20></ICMS><PIS><PISNT><CST>06</CST></PISNT></PIS><COFINS><COFINSNT><CST>06</CST></COFINSNT></COFINS></imposto></det><det nItem="3"><prod><cProd>7891079013083</cProd><cEAN>7891079013083</cEAN><xProd>491189-CUP NOOD COST C/M.CHURRASCO    NISSIN            03X68</xProd><NCM>19023000</NCM><CEST>1704700</CEST><indEscala>S</indEscala><CFOP>5102</CFOP><uCom>DP3</uCom><qCom>1.0000</qCom><vUnCom>7.7700</vUnCom><vProd>7.77</vProd><cEANTrib>7891079013083</cEANTrib><uTrib>UNID</uTrib><qTrib>3.0000</qTrib><vUnTrib>2.5900000001</vUnTrib><vOutro>0.11</vOutro><indTot>1</indTot></prod><imposto><vTotTrib>0.55</vTotTrib><ICMS><ICMS20><orig>0</orig><CST>20</CST><modBC>3</modBC><pRedBC>41.66</pRedBC><vBC>4.60</vBC><pICMS>12.00</pICMS><vICMS>0.55</vICMS></ICMS20></ICMS><PIS><PISNT><CST>06</CST></PISNT></PIS><COFINS><COFINSNT><CST>06</CST></COFINSNT></COFINS></imposto></det><det nItem="4"><prod><cProd>7891079013106</cProd><cEAN>7891079013106</cEAN><xProd>491190-CUP NOOD YAKISSOBA TRADICIONAL NISSIN            03X70</xProd><NCM>19023000</NCM><CEST>1704700</CEST><indEscala>S</indEscala><CFOP>5102</CFOP><uCom>DP3</uCom><qCom>1.0000</qCom><vUnCom>7.7700</vUnCom><vProd>7.77</vProd><cEANTrib>7891079013106</cEANTrib><uTrib>UNID</uTrib><qTrib>3.0000</qTrib><vUnTrib>2.5900000001</vUnTrib><vOutro>0.11</vOutro><indTot>1</indTot></prod><imposto><vTotTrib>0.55</vTotTrib><ICMS><ICMS20><orig>0</orig><CST>20</CST><modBC>3</modBC><pRedBC>41.66</pRedBC><vBC>4.60</vBC><pICMS>12.00</pICMS><vICMS>0.55</vICMS></ICMS20></ICMS><PIS><PISNT><CST>06</CST></PISNT></PIS><COFINS><COFINSNT><CST>06</CST></COFINSNT></COFINS></imposto></det><det nItem="5"><prod><cProd>7891079013113</cProd><cEAN>7891079013113</cEAN><xProd>491192-CUP NOODLES CHEDDAR            NISSIN            03X69</xProd><NCM>19023000</NCM><CEST>1704700</CEST><indEscala>S</indEscala><CFOP>5102</CFOP><uCom>DP3</uCom><qCom>1.0000</qCom><vUnCom>7.7700</vUnCom><vProd>7.77</vProd><cEANTrib>7891079013113</cEANTrib><uTrib>UNID</uTrib><qTrib>3.0000</qTrib><vUnTrib>2.5900000001</vUnTrib><vOutro>0.11</vOutro><indTot>1</indTot></prod><imposto><vTotTrib>0.55</vTotTrib><ICMS><ICMS20><orig>0</orig><CST>20</CST><modBC>3</modBC><pRedBC>41.66</pRedBC><vBC>4.60</vBC><pICMS>12.00</pICMS><vICMS>0.55</vICMS></ICMS20></ICMS><PIS><PISNT><CST>06</CST></PISNT></PIS><COFINS><COFINSNT><CST>06</CST></COFINSNT></COFINS></imposto></det><det nItem="6"><prod><cProd>7891079013045</cProd><cEAN>7891079013045</cEAN><xProd>491193-CUP NOODLES FRANGO TERIYAKI    NISSIN            03X72</xProd><NCM>19023000</NCM><CEST>1704700</CEST><indEscala>S</indEscala><CFOP>5102</CFOP><uCom>DP3</uCom><qCom>1.0000</qCom><vUnCom>7.7700</vUnCom><vProd>7.77</vProd><cEANTrib>7891079013045</cEANTrib><uTrib>UNID</uTrib><qTrib>3.0000</qTrib><vUnTrib>2.5900000001</vUnTrib><vOutro>0.11</vOutro><indTot>1</indTot></prod><imposto><vTotTrib>0.55</vTotTrib><ICMS><ICMS20><orig>0</orig><CST>20</CST><modBC>3</modBC><pRedBC>41.66</pRedBC><vBC>4.60</vBC><pICMS>12.00</pICMS><vICMS>0.55</vICMS></ICMS20></ICMS><PIS><PISNT><CST>06</CST></PISNT></PIS><COFINS><COFINSNT><CST>06</CST></COFINSNT></COFINS></imposto></det><det nItem="7"><prod><cProd>7891079013069</cProd><cEAN>7891079013069</cEAN><xProd>491195-CUP NOODLES GALINHA C PICANTE  NISSIN            03X68</xProd><NCM>19023000</NCM><CEST>1704700</CEST><indEscala>S</indEscala><CFOP>5102</CFOP><uCom>DP3</uCom><qCom>1.0000</qCom><vUnCom>7.7700</vUnCom><vProd>7.77</vProd><cEANTrib>7891079013069</cEANTrib><uTrib>UNID</uTrib><qTrib>3.0000</qTrib><vUnTrib>2.5900000001</vUnTrib><vOutro>0.11</vOutro><indTot>1</indTot></prod><imposto><vTotTrib>0.55</vTotTrib><ICMS><ICMS20><orig>0</orig><CST>20</CST><modBC>3</modBC><pRedBC>41.66</pRedBC><vBC>4.60</vBC><pICMS>12.00</pICMS><vICMS>0.55</vICMS></ICMS20></ICMS><PIS><PISNT><CST>06</CST></PISNT></PIS><COFINS><COFINSNT><CST>06</CST></COFINSNT></COFINS></imposto></det><det nItem="8"><prod><cProd>7891079013090</cProd><cEAN>7891079013090</cEAN><xProd>491196-CUP NOODLES LEGUMES C AZEITE   NISSIN            03X67</xProd><NCM>19023000</NCM><CEST>1704700</CEST><indEscala>S</indEscala><CFOP>5102</CFOP><uCom>DP3</uCom><qCom>1.0000</qCom><vUnCom>7.7700</vUnCom><vProd>7.77</vProd><cEANTrib>7891079013090</cEANTrib><uTrib>UNID</uTrib><qTrib>3.0000</qTrib><vUnTrib>2.5900000001</vUnTrib><vOutro>0.11</vOutro><indTot>1</indTot></prod><imposto><vTotTrib>0.55</vTotTrib><ICMS><ICMS20><orig>0</orig><CST>20</CST><modBC>3</modBC><pRedBC>41.66</pRedBC><vBC>4.60</vBC><pICMS>12.00</pICMS><vICMS>0.55</vICMS></ICMS20></ICMS><PIS><PISNT><CST>06</CST></PISNT></PIS><COFINS><COFINSNT><CST>06</CST></COFINSNT></COFINS></imposto></det><det nItem="9"><prod><cProd>7896336012533</cProd><cEAN>7896336012533</cEAN><xProd>261453-PACOQUITA QUAD EMB 432G        SANTA HELENA    01X432G</xProd><NCM>17049090</NCM><CFOP>5102</CFOP><uCom>UNID</uCom><qCom>1.0000</qCom><vUnCom>8.7400</vUnCom><vProd>8.74</vProd><cEANTrib>7896336012533</cEANTrib><uTrib>UNID</uTrib><qTrib>1.0000</qTrib><vUnTrib>8.7400000001</vUnTrib><vOutro>0.11</vOutro><indTot>1</indTot></prod><imposto><vTotTrib>1.86</vTotTrib><ICMS><ICMS20><orig>0</orig><CST>20</CST><modBC>3</modBC><pRedBC>29.41</pRedBC><vBC>6.25</vBC><pICMS>17.00</pICMS><vICMS>1.06</vICMS></ICMS20></ICMS><PIS><PISAliq><CST>01</CST><vBC>8.74</vBC><pPIS>1.65</pPIS><vPIS>0.14</vPIS></PISAliq></PIS><COFINS><COFINSAliq><CST>01</CST><vBC>8.74</vBC><pCOFINS>7.60</pCOFINS><vCOFINS>0.66</vCOFINS></COFINSAliq></COFINS></imposto></det><det nItem="10"><prod><cProd>7891098010575</cProd><cEAN>7891098010575</cEAN><xProd>373803-CHA CAMOMILA                   LEAO JUNIOR       03X15</xProd><NCM>12119090</NCM><CEST>1709700</CEST><indEscala>S</indEscala><CFOP>5910</CFOP><uCom>DP3</uCom><qCom>1.0000</qCom><vUnCom>10.7700</vUnCom><vProd>10.77</vProd><cEANTrib>7891098010575</cEANTrib><uTrib>UNID</uTrib><qTrib>3.0000</qTrib><vUnTrib>3.5900000001</vUnTrib><indTot>1</indTot></prod><imposto><vTotTrib>1.29</vTotTrib><ICMS><ICMS20><orig>0</orig><CST>20</CST><modBC>3</modBC><pRedBC>29.41</pRedBC><vBC>7.61</vBC><pICMS>17.00</pICMS><vICMS>1.29</vICMS></ICMS20></ICMS><PIS><PISNT><CST>08</CST></PISNT></PIS><COFINS><COFINSNT><CST>08</CST></COFINSNT></COFINS></imposto><infAdProd>*** ITEM BONIFICADO ***</infAdProd></det><det nItem="11"><prod><cProd>9002490100490</cProd><cEAN>09002490100445</cEAN><xProd>700004-RED BULL BR 4PACK              RED BULL        6X4X250</xProd><NCM>22029900</NCM><CEST>0301300</CEST><indEscala>S</indEscala><CFOP>5405</CFOP><uCom>CX24</uCom><qCom>3.0000</qCom><vUnCom>121.2000</vUnCom><vProd>363.60</vProd><cEANTrib>9002490100490</cEANTrib><uTrib>UNID</uTrib><qTrib>72.0000</qTrib><vUnTrib>5.0500000001</vUnTrib><vOutro>0.11</vOutro><indTot>1</indTot></prod><imposto><vTotTrib>28.92</vTotTrib><ICMS><ICMS60><orig>2</orig><CST>60</CST><vBCSTRet>547.20</vBCSTRet><pST>0.00</pST><vICMSSTRet>85.48</vICMSSTRet></ICMS60></ICMS><PIS><PISAliq><CST>01</CST><vBC>278.12</vBC><pPIS>1.86</pPIS><vPIS>5.17</vPIS></PISAliq></PIS><COFINS><COFINSAliq><CST>01</CST><vBC>278.12</vBC><pCOFINS>8.54</pCOFINS><vCOFINS>23.75</vCOFINS></COFINSAliq></COFINS></imposto><infAdProd>Valor do ICMS nao incluso na base de calculo do PIS e COFINS: Mandado de seguranca 0003238.90.20064.04.72.03 e 5003777.75.2017.04.4.72.03</infAdProd></det><det nItem="12"><prod><cProd>9002490222093</cProd><cEAN>09002490220792</cEAN><xProd>700030-RED BULL RED TRAY              RED BULL      06X04X250</xProd><NCM>22029900</NCM><CEST>0301300</CEST><indEscala>S</indEscala><CFOP>5405</CFOP><uCom>CX24</uCom><qCom>1.0000</qCom><vUnCom>121.2000</vUnCom><vProd>121.20</vProd><cEANTrib>9002490222093</cEANTrib><uTrib>UNID</uTrib><qTrib>24.0000</qTrib><vUnTrib>5.0500000001</vUnTrib><vOutro>0.11</vOutro><indTot>1</indTot></prod><imposto><vTotTrib>9.64</vTotTrib><ICMS><ICMS60><orig>0</orig><CST>60</CST><vBCSTRet>182.40</vBCSTRet><pST>0.00</pST><vICMSSTRet>28.38</vICMSSTRet></ICMS60></ICMS><PIS><PISAliq><CST>01</CST><vBC>92.82</vBC><pPIS>1.86</pPIS><vPIS>1.72</vPIS></PISAliq></PIS><COFINS><COFINSAliq><CST>01</CST><vBC>92.82</vBC><pCOFINS>8.54</pCOFINS><vCOFINS>7.92</vCOFINS></COFINSAliq></COFINS></imposto><infAdProd>Valor do ICMS nao incluso na base de calculo do PIS e COFINS: Mandado de seguranca 0003238.90.20064.04.72.03 e 5003777.75.2017.04.4.72.03</infAdProd></det><det nItem="13"><prod><cProd>9002490225094</cProd><cEAN>09002490200398</cEAN><xProd>700081-RED BULL SUGAR FREE 4PACK      RED BULL      06X04X250</xProd><NCM>22029900</NCM><CEST>0301300</CEST><indEscala>S</indEscala><CFOP>5405</CFOP><uCom>CX24</uCom><qCom>2.0000</qCom><vUnCom>121.2000</vUnCom><vProd>242.40</vProd><cEANTrib>9002490225094</cEANTrib><uTrib>UNID</uTrib><qTrib>48.0000</qTrib><vUnTrib>5.0500000001</vUnTrib><vOutro>0.11</vOutro><indTot>1</indTot></prod><imposto><vTotTrib>19.30</vTotTrib><ICMS><ICMS60><orig>2</orig><CST>60</CST><vBCSTRet>364.80</vBCSTRet><pST>0.00</pST><vICMSSTRet>56.77</vICMSSTRet></ICMS60></ICMS><PIS><PISAliq><CST>01</CST><vBC>185.63</vBC><pPIS>1.86</pPIS><vPIS>3.45</vPIS></PISAliq></PIS><COFINS><COFINSAliq><CST>01</CST><vBC>185.63</vBC><pCOFINS>8.54</pCOFINS><vCOFINS>15.85</vCOFINS></COFINSAliq></COFINS></imposto><infAdProd>Valor do ICMS nao incluso na base de calculo do PIS e COFINS: Mandado de seguranca 0003238.90.20064.04.72.03 e 5003777.75.2017.04.4.72.03</infAdProd></det><det nItem="14"><prod><cProd>9002490235208</cProd><cEAN>09002490235215</cEAN><xProd>700087-RED BULL ACAI 4PACK            RED BULL       06X4X250</xProd><NCM>22029900</NCM><CEST>0301300</CEST><indEscala>S</indEscala><CFOP>5405</CFOP><uCom>CX24</uCom><qCom>1.0000</qCom><vUnCom>121.2000</vUnCom><vProd>121.20</vProd><cEANTrib>9002490235208</cEANTrib><uTrib>UNID</uTrib><qTrib>24.0000</qTrib><vUnTrib>5.0500000001</vUnTrib><vOutro>0.11</vOutro><indTot>1</indTot></prod><imposto><vTotTrib>9.63</vTotTrib><ICMS><ICMS60><orig>2</orig><CST>60</CST><vBCSTRet>182.40</vBCSTRet><pST>0.00</pST><vICMSSTRet>28.49</vICMSSTRet></ICMS60></ICMS><PIS><PISAliq><CST>01</CST><vBC>92.71</vBC><pPIS>1.86</pPIS><vPIS>1.72</vPIS></PISAliq></PIS><COFINS><COFINSAliq><CST>01</CST><vBC>92.71</vBC><pCOFINS>8.54</pCOFINS><vCOFINS>7.91</vCOFINS></COFINSAliq></COFINS></imposto><infAdProd>Valor do ICMS nao incluso na base de calculo do PIS e COFINS: Mandado de seguranca 0003238.90.20064.04.72.03 e 5003777.75.2017.04.4.72.03</infAdProd></det><det nItem="15"><prod><cProd>9002490225100</cProd><cEAN>09002490225100</cEAN><xProd>700105-RED BULL BR E DRINK 4PACK      RED BULL      06X04X355</xProd><NCM>22029900</NCM><CEST>0301300</CEST><indEscala>S</indEscala><CFOP>5405</CFOP><uCom>CX24</uCom><qCom>1.0000</qCom><vUnCom>159.6000</vUnCom><vProd>159.60</vProd><cEANTrib>9002490225100</cEANTrib><uTrib>UNID</uTrib><qTrib>24.0000</qTrib><vUnTrib>6.6500000001</vUnTrib><vOutro>0.11</vOutro><indTot>1</indTot></prod><imposto><vTotTrib>12.99</vTotTrib><ICMS><ICMS60><orig>3</orig><CST>60</CST><vBCSTRet>221.28</vBCSTRet><pST>0.00</pST><vICMSSTRet>34.55</vICMSSTRet></ICMS60></ICMS><PIS><PISAliq><CST>01</CST><vBC>125.05</vBC><pPIS>1.86</pPIS><vPIS>2.32</vPIS></PISAliq></PIS><COFINS><COFINSAliq><CST>01</CST><vBC>125.05</vBC><pCOFINS>8.54</pCOFINS><vCOFINS>10.67</vCOFINS></COFINSAliq></COFINS></imposto><infAdProd>Valor do ICMS nao incluso na base de calculo do PIS e COFINS: Mandado de seguranca 0003238.90.20064.04.72.03 e 5003777.75.2017.04.4.72.03</infAdProd></det><det nItem="16"><prod><cProd>9002490243678</cProd><cEAN>09002490244552</cEAN><xProd>700355-RED BULL SUGAR FREE 4PACK      RED BULL      06X04X355</xProd><NCM>22029900</NCM><CEST>0301300</CEST><indEscala>S</indEscala><CFOP>5405</CFOP><uCom>CX24</uCom><qCom>1.0000</qCom><vUnCom>159.6000</vUnCom><vProd>159.60</vProd><cEANTrib>9002490243678</cEANTrib><uTrib>UNID</uTrib><qTrib>24.0000</qTrib><vUnTrib>6.6500000001</vUnTrib><vOutro>0.11</vOutro><indTot>1</indTot></prod><imposto><vTotTrib>13.01</vTotTrib><ICMS><ICMS60><orig>2</orig><CST>60</CST><vBCSTRet>221.28</vBCSTRet><pST>0.00</pST><vICMSSTRet>34.36</vICMSSTRet></ICMS60></ICMS><PIS><PISAliq><CST>01</CST><vBC>125.24</vBC><pPIS>1.86</pPIS><vPIS>2.32</vPIS></PISAliq></PIS><COFINS><COFINSAliq><CST>01</CST><vBC>125.24</vBC><pCOFINS>8.54</pCOFINS><vCOFINS>10.69</vCOFINS></COFINSAliq></COFINS></imposto><infAdProd>Valor do ICMS nao incluso na base de calculo do PIS e COFINS: Mandado de seguranca 0003238.90.20064.04.72.03 e 5003777.75.2017.04.4.72.03</infAdProd></det><det nItem="17"><prod><cProd>9002490214166</cProd><cEAN>09002490214173</cEAN><xProd>700013-RED BULL BR E DRINK 473        RED BULL         12X473</xProd><NCM>22029900</NCM><CEST>0301300</CEST><indEscala>S</indEscala><CFOP>5405</CFOP><uCom>CX12</uCom><qCom>1.0000</qCom><vUnCom>99.4800</vUnCom><vProd>99.48</vProd><cEANTrib>9002490214166</cEANTrib><uTrib>UNID</uTrib><qTrib>12.0000</qTrib><vUnTrib>8.2900000001</vUnTrib><vOutro>0.11</vOutro><indTot>1</indTot></prod><imposto><vTotTrib>8.11</vTotTrib><ICMS><ICMS60><orig>3</orig><CST>60</CST><vBCSTRet>138.12</vBCSTRet><pST>0.00</pST><vICMSSTRet>21.43</vICMSSTRet></ICMS60></ICMS><PIS><PISAliq><CST>01</CST><vBC>78.05</vBC><pPIS>1.86</pPIS><vPIS>1.45</vPIS></PISAliq></PIS><COFINS><COFINSAliq><CST>01</CST><vBC>78.05</vBC><pCOFINS>8.54</pCOFINS><vCOFINS>6.66</vCOFINS></COFINSAliq></COFINS></imposto><infAdProd>Valor do ICMS nao incluso na base de calculo do PIS e COFINS: Mandado de seguranca 0003238.90.20064.04.72.03 e 5003777.75.2017.04.4.72.03</infAdProd></det><det nItem="18"><prod><cProd>7898629570461</cProd><cEAN>17898629570468</cEAN><xProd>310446-BALA GEL BANANA 100G           HARIBO           12X100</xProd><NCM>17049020</NCM><CFOP>5102</CFOP><uCom>CX12</uCom><qCom>1.0000</qCom><vUnCom>40.0600</vUnCom><vProd>40.06</vProd><cEANTrib>7898629570461</cEANTrib><uTrib>UNID</uTrib><qTrib>12.0000</qTrib><vUnTrib>3.3383333334</vUnTrib><vOutro>0.11</vOutro><indTot>1</indTot></prod><imposto><vTotTrib>8.52</vTotTrib><ICMS><ICMS20><orig>5</orig><CST>20</CST><modBC>3</modBC><pRedBC>29.41</pRedBC><vBC>28.36</vBC><pICMS>17.00</pICMS><vICMS>4.82</vICMS></ICMS20></ICMS><PIS><PISAliq><CST>01</CST><vBC>40.06</vBC><pPIS>1.65</pPIS><vPIS>0.66</vPIS></PISAliq></PIS><COFINS><COFINSAliq><CST>01</CST><vBC>40.06</vBC><pCOFINS>7.60</pCOFINS><vCOFINS>3.04</vCOFINS></COFINSAliq></COFINS></imposto></det><det nItem="19"><prod><cProd>7898629570690</cProd><cEAN>17898629570697</cEAN><xProd>310456-BALLA KIT URSINHOS OURO L3P2   HARIBO           06X300</xProd><NCM>17049020</NCM><CFOP>5102</CFOP><uCom>CX6</uCom><qCom>1.0000</qCom><vUnCom>40.7600</vUnCom><vProd>40.76</vProd><cEANTrib>7898629570690</cEANTrib><uTrib>UNID</uTrib><qTrib>6.0000</qTrib><vUnTrib>6.7933333334</vUnTrib><vOutro>0.11</vOutro><indTot>1</indTot></prod><imposto><vTotTrib>8.66</vTotTrib><ICMS><ICMS20><orig>5</orig><CST>20</CST><modBC>3</modBC><pRedBC>29.41</pRedBC><vBC>28.85</vBC><pICMS>17.00</pICMS><vICMS>4.90</vICMS></ICMS20></ICMS><PIS><PISAliq><CST>01</CST><vBC>40.76</vBC><pPIS>1.65</pPIS><vPIS>0.67</vPIS></PISAliq></PIS><COFINS><COFINSAliq><CST>01</CST><vBC>40.76</vBC><pCOFINS>7.60</pCOFINS><vCOFINS>3.09</vCOFINS></COFINSAliq></COFINS></imposto></det><det nItem="20"><prod><cProd>7898629570706</cProd><cEAN>17898629570703</cEAN><xProd>310457-BALLA KIT CREAM KISS L3P2      HARIBO           06X300</xProd><NCM>17049020</NCM><CFOP>5102</CFOP><uCom>CX6</uCom><qCom>1.0000</qCom><vUnCom>40.7600</vUnCom><vProd>40.76</vProd><cEANTrib>7898629570706</cEANTrib><uTrib>UNID</uTrib><qTrib>6.0000</qTrib><vUnTrib>6.7933333334</vUnTrib><vOutro>0.11</vOutro><indTot>1</indTot></prod><imposto><vTotTrib>8.66</vTotTrib><ICMS><ICMS20><orig>5</orig><CST>20</CST><modBC>3</modBC><pRedBC>29.41</pRedBC><vBC>28.85</vBC><pICMS>17.00</pICMS><vICMS>4.90</vICMS></ICMS20></ICMS><PIS><PISAliq><CST>01</CST><vBC>40.76</vBC><pPIS>1.65</pPIS><vPIS>0.67</vPIS></PISAliq></PIS><COFINS><COFINSAliq><CST>01</CST><vBC>40.76</vBC><pCOFINS>7.60</pCOFINS><vCOFINS>3.09</vCOFINS></COFINSAliq></COFINS></imposto></det><det nItem="21"><prod><cProd>7896000595973</cProd><cEAN>7896000595973</cEAN><xProd>561020-FRUIT SHOOT MORANGO            MAGUARY        01X275ML</xProd><NCM>22021000</NCM><CEST>1711100</CEST><indEscala>S</indEscala><CFOP>5910</CFOP><uCom>UNID</uCom><qCom>2.0000</qCom><vUnCom>1.8400</vUnCom><vProd>3.68</vProd><cEANTrib>7896000595973</cEANTrib><uTrib>UNID</uTrib><qTrib>2.0000</qTrib><vUnTrib>1.8400000001</vUnTrib><indTot>1</indTot></prod><imposto><vTotTrib>0.44</vTotTrib><ICMS><ICMS20><orig>0</orig><CST>20</CST><modBC>3</modBC><pRedBC>29.41</pRedBC><vBC>2.60</vBC><pICMS>17.00</pICMS><vICMS>0.44</vICMS></ICMS20></ICMS><PIS><PISNT><CST>08</CST></PISNT></PIS><COFINS><COFINSNT><CST>08</CST></COFINSNT></COFINS></imposto><infAdProd>*** ITEM BONIFICADO ***</infAdProd></det><det nItem="22"><prod><cProd>7896000595959</cProd><cEAN>7896000595959</cEAN><xProd>561021-FRUIT SHOOT MARACUJA           MAGUARY        01X275ML</xProd><NCM>22021000</NCM><CEST>1711100</CEST><indEscala>S</indEscala><CFOP>5910</CFOP><uCom>UNID</uCom><qCom>2.0000</qCom><vUnCom>1.8400</vUnCom><vProd>3.68</vProd><cEANTrib>7896000595959</cEANTrib><uTrib>UNID</uTrib><qTrib>2.0000</qTrib><vUnTrib>1.8400000001</vUnTrib><indTot>1</indTot></prod><imposto><vTotTrib>0.44</vTotTrib><ICMS><ICMS20><orig>0</orig><CST>20</CST><modBC>3</modBC><pRedBC>29.41</pRedBC><vBC>2.60</vBC><pICMS>17.00</pICMS><vICMS>0.44</vICMS></ICMS20></ICMS><PIS><PISNT><CST>08</CST></PISNT></PIS><COFINS><COFINSNT><CST>08</CST></COFINSNT></COFINS></imposto><infAdProd>*** ITEM BONIFICADO ***</infAdProd></det><det nItem="23"><prod><cProd>7896000595966</cProd><cEAN>7896000595966</cEAN><xProd>561023-FRUIT SHOOT LARANJA            MAGUARY        01X275ML</xProd><NCM>22021000</NCM><CEST>1711100</CEST><indEscala>S</indEscala><CFOP>5910</CFOP><uCom>UNID</uCom><qCom>2.0000</qCom><vUnCom>1.8400</vUnCom><vProd>3.68</vProd><cEANTrib>7896000595966</cEANTrib><uTrib>UNID</uTrib><qTrib>2.0000</qTrib><vUnTrib>1.8400000001</vUnTrib><indTot>1</indTot></prod><imposto><vTotTrib>0.44</vTotTrib><ICMS><ICMS20><orig>0</orig><CST>20</CST><modBC>3</modBC><pRedBC>29.41</pRedBC><vBC>2.60</vBC><pICMS>17.00</pICMS><vICMS>0.44</vICMS></ICMS20></ICMS><PIS><PISNT><CST>08</CST></PISNT></PIS><COFINS><COFINSNT><CST>08</CST></COFINSNT></COFINS></imposto><infAdProd>*** ITEM BONIFICADO ***</infAdProd></det><det nItem="24"><prod><cProd>7894650005668</cProd><cEAN>7894650005668</cEAN><xProd>281543-GL GEL CITRUS                  SCJOHNSON        01X70G</xProd><NCM>33074900</NCM><CFOP>5102</CFOP><uCom>UNID</uCom><qCom>6.0000</qCom><vUnCom>4.3500</vUnCom><vProd>26.10</vProd><cEANTrib>7894650005668</cEANTrib><uTrib>UNID</uTrib><qTrib>6.0000</qTrib><vUnTrib>4.3500000001</vUnTrib><vOutro>0.11</vOutro><indTot>1</indTot></prod><imposto><vTotTrib>3.15</vTotTrib><ICMS><ICMS20><orig>4</orig><CST>20</CST><modBC>3</modBC><pRedBC>52.00</pRedBC><vBC>12.59</vBC><pICMS>25.00</pICMS><vICMS>3.15</vICMS></ICMS20></ICMS><PIS><PISNT><CST>04</CST></PISNT></PIS><COFINS><COFINSNT><CST>04</CST></COFINSNT></COFINS></imposto></det><det nItem="25"><prod><cProd>7506161218702</cProd><cEAN>7506161218702</cEAN><xProd>621828-OVO CHOCO PATRULHA CAN         PAW PATROL       12X20G</xProd><NCM>18069000</NCM><CEST>1700501</CEST><indEscala>S</indEscala><CFOP>5102</CFOP><uCom>DP12</uCom><qCom>1.0000</qCom><vUnCom>55.5700</vUnCom><vProd>55.57</vProd><cEANTrib>7506161218702</cEANTrib><uTrib>UNID</uTrib><qTrib>12.0000</qTrib><vUnTrib>4.6308333334</vUnTrib><vOutro>0.15</vOutro><indTot>1</indTot></prod><imposto><vTotTrib>11.82</vTotTrib><ICMS><ICMS20><orig>2</orig><CST>20</CST><modBC>3</modBC><pRedBC>29.41</pRedBC><vBC>39.34</vBC><pICMS>17.00</pICMS><vICMS>6.69</vICMS></ICMS20></ICMS><PIS><PISAliq><CST>01</CST><vBC>55.57</vBC><pPIS>1.65</pPIS><vPIS>0.91</vPIS></PISAliq></PIS><COFINS><COFINSAliq><CST>01</CST><vBC>55.57</vBC><pCOFINS>7.60</pCOFINS><vCOFINS>4.22</vCOFINS></COFINSAliq></COFINS></imposto></det><total><ICMSTot><vBC>205.51</vBC><vICMS>33.63</vICMS><vICMSDeson>0.00</vICMSDeson><vFCPUFDest>0.00</vFCPUFDest><vICMSUFDest>0.00</vICMSUFDest><vICMSUFRemet>0.00</vICMSUFRemet><vFCP>0.00</vFCP><vBCST>0.00</vBCST><vST>0.00</vST><vFCPST>0.00</vFCPST><vFCPSTRet>0.00</vFCPSTRet><vProd>1578.58</vProd><vFrete>0.00</vFrete><vSeg>0.00</vSeg><vDesc>0.00</vDesc><vII>0</vII><vIPI>0.00</vIPI><vIPIDevol>0.00</vIPIDevol><vPIS>21.20</vPIS><vCOFINS>97.55</vCOFINS><vOutro>2.35</vOutro><vNF>1580.93</vNF><vTotTrib>152.38</vTotTrib></ICMSTot></total><transp><modFrete>0</modFrete><vol><qVol>38</qVol><pesoL>75.989</pesoL><pesoB>83.160</pesoB></vol></transp><cobr><fat><nFat>317091</nFat><vOrig>1580.93</vOrig><vDesc>21.81</vDesc><vLiq>1559.12</vLiq></fat><dup><nDup>001</nDup><dVenc>2019-09-17</dVenc><vDup>1559.12</vDup></dup></cobr><pag><detPag><tPag>15</tPag><vPag>1580.93</vPag></detPag></pag><infAdic><infAdFisco>/S.Trib.= BASE ******1.857,48 Vlr ICMS ST ****289,46 - FAT: 28/ Dias BOLETO BRADESCO CLI: 9.376-90 ROTA: JB111 CHAPECO 01.* 0439 0 MAICON S.SILVA 102666 Pedido: 1.991 * Ped.Cliente: BASE DE CALCULO DO ICMS REDUZIDA, PRODUTO DA CESTA BASICA, RICMS/SC, ANEXO 02 ART. 11-A ICMS REDUCAO DA BASE DE CALCULO ATACADISTAS E DIST.,RICMS/SCANEXO 2, ARTIGOS 90 E 91. PROC.SEF 021305/2013.TTD NUMERO 135000001245788. VIGENCIA: PRAZO INDETERMINADO IMPOSTO RETIDO POR SUBSTITUICAO TRIBUTARIA RICMS-SC/01-ANEXO1-A. SUBSTITUICAO TRIBUTARIA CONFORME DECRETO 3174/2010.ICMSRETIDO ANTERIORMENTE  Venda:         1.556,77 / Bonificacao:            21,81 Fatura: 0001 - 1975496-1 Vecto: 2019-09-17 Valor: 1559.12</infAdFisco><obsCont xCampo="FATURA"><xTexto>28/         Dias   BOLETO BRADESCO</xTexto></obsCont><obsCont xCampo="FANTASIA"><xTexto>POSTO PERIZZOLO</xTexto></obsCont><obsCont xCampo="CODCLI"><xTexto>9.376-90</xTexto></obsCont><obsCont xCampo="ROTA"><xTexto>ROTA: JB111 CHAPECO 01</xTexto></obsCont><obsFisco xCampo="FISCO2"><xTexto>S.Trib.= BASE ******1.857,48 Vlr ICMS ST ****289,46 -</xTexto></obsFisco><obsFisco xCampo="BASEST"><xTexto>0.00</xTexto></obsFisco><obsFisco xCampo="ICMSST"><xTexto>0.00</xTexto></obsFisco></infAdic></infNFe><Signature xmlns="http://www.w3.org/2000/09/xmldsig#"><SignedInfo><CanonicalizationMethod Algorithm="http://www.w3.org/TR/2001/REC-xml-c14n-20010315" /><SignatureMethod Algorithm="http://www.w3.org/2000/09/xmldsig#rsa-sha1" /><Reference URI="#NFe42190877887412000110550060003170911000211396"><Transforms><Transform Algorithm="http://www.w3.org/2000/09/xmldsig#enveloped-signature" /><Transform Algorithm="http://www.w3.org/TR/2001/REC-xml-c14n-20010315" /></Transforms><DigestMethod Algorithm="http://www.w3.org/2000/09/xmldsig#sha1" /><DigestValue>CfCfLfDCw//018tlHKT4yQXmS0U=</DigestValue></Reference></SignedInfo><SignatureValue>YbhFsKauICsOiafKzdsUGjE6SsOPYxP5SsOlqZzBB2MFgZmjQx9AaUwSHcX6HGfsUKDj1EICm/rX
Vu3oTr7wXtpYTP+E/I9InNfXDiYrwQ5N37MmT7BIxvaIpPVcUrKkOQofWgNxEFjY++Njk5GZ2SpC
VaPrawvELze7PH26Ou0+8JSaE/yxezB3aRf1rFJGD0xzBxJMA4IDbwxl7NLckPfS9ZWiGowmUhLi
Q5NRYCY6bE7yg+AU4LdDP/XFBupsxqLaAdBPZVJ+dy0qz6LSDLZz8OPZ01xbaDVhHJYxSpEqLxz2
Y3/TBnFrHpOY907/v8jIxPkE5mUz7sIeZQSOyg==</SignatureValue><KeyInfo><X509Data><X509Certificate>MIIIOzCCBiOgAwIBAgIQR2AAPtCn+d35Cxl0LEBAyDANBgkqhkiG9w0BAQsFADCBgDELMAkGA1UE
BhMCQlIxEzARBgNVBAoTCklDUC1CcmFzaWwxNjA0BgNVBAsTLVNlY3JldGFyaWEgZGEgUmVjZWl0
YSBGZWRlcmFsIGRvIEJyYXNpbCAtIFJGQjEkMCIGA1UEAxMbQUMgSW5zdGl0dXRvIEZlbmFjb24g
UkZCIEczMB4XDTE4MTIwMzE2MTE1NVoXDTE5MTIwMzE2MTE1NVowgfUxCzAJBgNVBAYTAkJSMRMw
EQYDVQQKDApJQ1AtQnJhc2lsMQswCQYDVQQIDAJTQzEQMA4GA1UEBwwHSm9hY2FiYTE2MDQGA1UE
CwwtU2VjcmV0YXJpYSBkYSBSZWNlaXRhIEZlZGVyYWwgZG8gQnJhc2lsIC0gUkZCMRYwFAYDVQQL
DA1SRkIgZS1DTlBKIEExMSUwIwYDVQQLDBxBdXRlbnRpY2FkbyBwb3IgQVIgU2VzY29uIFNDMTsw
OQYDVQQDDDJERVlDT04gQ09NRVJDSU8gRSBESVNUUklCVUlDQU8gTFREQTo3Nzg4NzQxMjAwMDEx
MDCCASIwDQYJKoZIhvcNAQEBBQADggEPADCCAQoCggEBALLxcwQM2lsFYQVSongknLmrh7HVKwXr
KIO5qnJxaIPyiI0MiZz4E6H7ZL1arcw+al1CMyoqojd2TrYx6Na7ThHfbt46y2Q75+QdOtFFhkU8
cEnpecDcF1JeStv/sLduStMKhWVFc1IqxlirB8oHQHg3AQG3g3bSCaWsQlmZnWhMqkBPN8iyadXR
vhnVb3Tb47avYA4k3qYa42yA9zDIR54UHVRDO8clJJ0ZXKK32JzNzZbHbuEzUB5kRWR9wb8yh7uu
UFLy4rzTkz3kLo6qs8vCyJ6me2zC2XrlSDniOSRNCyTJgkxRxOxGXD2QZN/4gl+TgyDOxjM+ZWcz
ni4t9FMCAwEAAaOCAzgwggM0MIHCBgNVHREEgbowgbegPQYFYEwBAwSgNAQyMTMxMjE5NTE1NDU1
NDI2ODkzNDAwMDAwMDAwMDAwMDAwMDAwMDAwNTQ3Nzk5U1NQU0OgHwYFYEwBAwKgFgQUTklMVkEg
TFVDSUEgUEVHT1JBUk+gGQYFYEwBAwOgEAQONzc4ODc0MTIwMDAxMTCgFwYFYEwBAwegDgQMMDAw
MDAwMDAwMDAwgSFjbGFpci5zYW50b3NAZ3J1cG9wZWdvcmFyby5jb20uYnIwCQYDVR0TBAIwADAf
BgNVHSMEGDAWgBQmx5Q9eod+f0t4ioc94M+1zqmw2jCBhgYDVR0gBH8wfTB7BgZgTAECASIwcTBv
BggrBgEFBQcCARZjaHR0cDovL2ljcC1icmFzaWwuYWNmZW5hY29uLmNvbS5ici9yZXBvc2l0b3Jp
by9kcGMvQUMtSW5zdGl0dXRvLUZlbmFjb24tUkZCL0RQQ19BQ19JRmVuYWNvbl9SRkIucGRmMIHK
BgNVHR8EgcIwgb8wXqBcoFqGWGh0dHA6Ly9pY3AtYnJhc2lsLmFjZmVuYWNvbi5jb20uYnIvcmVw
b3NpdG9yaW8vbGNyL0FDSW5zdGl0dXRvRmVuYWNvblJGQkczL0xhdGVzdENSTC5jcmwwXaBboFmG
V2h0dHA6Ly9pY3AtYnJhc2lsLm91dHJhbGNyLmNvbS5ici9yZXBvc2l0b3Jpby9sY3IvQUNJbnN0
aXR1dG9GZW5hY29uUkZCRzMvTGF0ZXN0Q1JMLmNybDAOBgNVHQ8BAf8EBAMCBeAwHQYDVR0lBBYw
FAYIKwYBBQUHAwIGCCsGAQUFBwMEMIG7BggrBgEFBQcBAQSBrjCBqzBmBggrBgEFBQcwAoZaaHR0
cDovL2ljcC1icmFzaWwuYWNmZW5hY29uLmNvbS5ici9yZXBvc2l0b3Jpby9jZXJ0aWZpY2Fkb3Mv
QUNfSW5zdGl0dXRvX0ZlbmFjb25fUkZCRzMucDdjMEEGCCsGAQUFBzABhjVodHRwOi8vb2NzcC1h
Yy1pbnN0aXR1dG8tZmVuYWNvbi1yZmIuY2VydGlzaWduLmNvbS5icjANBgkqhkiG9w0BAQsFAAOC
AgEAfCy5ka3hmmrZ5MCIGI7q5irOQ5roCtVsJ8EHav+56vQCY4cr+MmgVqDXyyZUk1NK6OQRsDSN
ls9toBtBTntyu/zOX/JAqtUH25mfhfvTz3pZwEwoW1c62FQxNzmKCDdREEtHow7eZaaEY6UYWmgM
GOY49ngEQ0QK/dpRlGqUZpCq+dmHNZ8SE3idwIoWDIjl0TvmhThx3MM6iKJ3YL7kZ1ioBiBZz4BP
XBa8+9xfMVNWrsh292Nbzw5SHFc45B1zYrsMdVkAOOXCb+uKw3DTOZNoFADajzwN1cDQbd4apxef
Lc66BpFXnv4qzdrnrB2zU//LLQVfcDso5n9wFVYn8CJ43I8scrOlj8VvOGekHsw7ObKNUfhhzArQ
dmGxImr8NwJ/M5BPSvNPnMk+DIXPwSCEImpFnD7HOpWOucRFELalSAjxcc2DuD1bSdw93geXo5pF
GQoXypLcrL95nfuvnlVRqi348zD/F+L4RZFHVyoull6lajwk2D8oBmssPPgTMSg1i17urTbCtSKO
/7xRI7wDeQDiVvT6F0GVdEO+JB8Z4D+p2NSE58Ge3SAbciLuLsZTeeUA4kHQpWkjpbaM7BF/afzV
Adglc/zUs+fwm6BXMZeB7CbCMldj7HqIAlfvVGcvPYzigc64Mb3d+jShqdzeCUA2iUCCVZ0EYz94
AbE=</X509Certificate></X509Data></KeyInfo></Signature></NFe><protNFe versao="4.00"><infProt Id="ID342190120931206"><tpAmb>1</tpAmb><verAplic>SVRS201907251349</verAplic><chNFe>42190877887412000110550060003170911000211396</chNFe><dhRecbto>2019-08-20T19:19:15-03:00</dhRecbto><nProt>342190120931206</nProt><digVal>CfCfLfDCw//018tlHKT4yQXmS0U=</digVal><cStat>100</cStat><xMotivo>Autorizado o uso da NF-e</xMotivo></infProt></protNFe></nfeProc>